{"golbat":{"usage":57.67845,"raw":264,"avg":0.324306785638,"vc":92,"abilities":[{"name":"Infiltrator","usage":88.836},{"name":"Inner Focus","usage":11.164}],"moves":[{"name":"Roost","usage":75.595},{"name":"Defog","usage":72.996},{"name":"Air Slash","usage":52.77},{"name":"Brave Bird","usage":47.202},{"name":"Whirlwind","usage":28.836},{"name":"U-turn","usage":26.829},{"name":"Nasty Plot","usage":25.271},{"name":"Sludge Bomb","usage":23.938},{"name":"Heat Wave","usage":23.879},{"name":"Taunt","usage":15.48},{"name":"Other","usage":7.205}],"items":[{"name":"Eviolite","usage":99.473},{"name":"Other","usage":0.527}],"spreads":[{"nature":"Timid","evs":{"hp":252,"atk":0,"def":0,"spa":4,"spd":0,"spe":252},"usage":27.499},{"nature":"Timid","evs":{"hp":0,"atk":0,"def":0,"spa":252,"spd":4,"spe":252},"usage":23.879},{"nature":"Jolly","evs":{"hp":248,"atk":0,"def":176,"spa":0,"spd":0,"spe":84},"usage":17.109},{"nature":"Jolly","evs":{"hp":252,"atk":0,"def":172,"spa":0,"spd":0,"spe":84},"usage":9.098},{"nature":"Impish","evs":{"hp":252,"atk":4,"def":252,"spa":0,"spd":0,"spe":0},"usage":8.591},{"nature":"Impish","evs":{"hp":252,"atk":0,"def":160,"spa":0,"spd":0,"spe":96},"usage":6.381},{"nature":"Other","evs":{"hp":null,"atk":null,"def":null,"spa":null,"spd":null,"spe":null},"usage":7.442}],"teammates":[{"name":"Raboot","usage":74.189},{"name":"Gurdurr","usage":64.072},{"name":"Piloswine","usage":36.979},{"name":"Ferroseed","usage":36.894},{"name":"Linoone-Galar","usage":28.696},{"name":"Thwackey","usage":27.179},{"name":"Duosion","usage":26.968},{"name":"Krokorok","usage":26.117},{"name":"Lampent","usage":26.117},{"name":"Metang","usage":26.117},{"name":"Electabuzz","usage":23.619}],"counters":[],"lead":{"usage":1.32782,"raw":6,"rawp":0.531}},"raboot":{"usage":53.52239,"raw":287,"avg":0.301158510174,"vc":92,"abilities":[{"name":"Libero","usage":100},{"name":"Blaze","usage":0}],"moves":[{"name":"High Jump Kick","usage":100},{"name":"Flare Blitz","usage":98.805},{"name":"U-turn","usage":73.855},{"name":"Gunk Shot","usage":55.551},{"name":"Sucker Punch","usage":51.435},{"name":"Assurance","usage":18.599},{"name":"Other","usage":1.756}],"items":[{"name":"Choice Band","usage":37.381},{"name":"Heavy-Duty Boots","usage":31.46},{"name":"Life Orb","usage":26.26},{"name":"Other","usage":4.899}],"spreads":[{"nature":"Jolly","evs":{"hp":0,"atk":252,"def":0,"spa":0,"spd":4,"spe":252},"usage":80.525},{"nature":"Jolly","evs":{"hp":0,"atk":252,"def":4,"spa":0,"spd":0,"spe":252},"usage":9.555},{"nature":"Adamant","evs":{"hp":0,"atk":252,"def":0,"spa":0,"spd":4,"spe":252},"usage":9.044},{"nature":"Other","evs":{"hp":null,"atk":null,"def":null,"spa":null,"spd":null,"spe":null},"usage":0.876}],"teammates":[{"name":"Golbat","usage":79.333},{"name":"Gurdurr","usage":63.036},{"name":"Piloswine","usage":39.774},{"name":"Ferroseed","usage":37.17},{"name":"Metang","usage":28.795},{"name":"Lampent","usage":27.928},{"name":"Krokorok","usage":27.928},{"name":"Linoone-Galar","usage":25.697},{"name":"Thwackey","usage":25.684},{"name":"Duosion","usage":23.337},{"name":"Electabuzz","usage":18.972}],"counters":[],"lead":{"usage":22.68,"raw":60,"rawp":5.31}},"gurdurr":{"usage":44.39474,"raw":240,"avg":0.314945522157,"vc":92,"abilities":[{"name":"Guts","usage":95.398},{"name":"Iron Fist","usage":4.602},{"name":"Sheer Force","usage":0}],"moves":[{"name":"Knock Off","usage":99.926},{"name":"Drain Punch","usage":99.926},{"name":"Mach Punch","usage":84.006},{"name":"Bulk Up","usage":39.51},{"name":"Poison Jab","usage":36.628},{"name":"Defog","usage":22.086},{"name":"Other","usage":17.918}],"items":[{"name":"Eviolite","usage":97.578},{"name":"Other","usage":2.422}],"spreads":[{"nature":"Adamant","evs":{"hp":252,"atk":252,"def":0,"spa":0,"spd":4,"spe":0},"usage":72.094},{"nature":"Adamant","evs":{"hp":252,"atk":116,"def":136,"spa":0,"spd":0,"spe":4},"usage":11.369},{"nature":"Adamant","evs":{"hp":252,"atk":252,"def":4,"spa":0,"spd":0,"spe":0},"usage":2.837},{"nature":"Adamant","evs":{"hp":236,"atk":252,"def":0,"spa":0,"spd":0,"spe":20},"usage":2.825},{"nature":"Adamant","evs":{"hp":252,"atk":20,"def":232,"spa":0,"spd":0,"spe":4},"usage":2.809},{"nature":"Adamant","evs":{"hp":236,"atk":252,"def":0,"spa":0,"spd":18,"spe":4},"usage":2.729},{"nature":"Other","evs":{"hp":null,"atk":null,"def":null,"spa":null,"spd":null,"spe":null},"usage":5.336}],"teammates":[{"name":"Golbat","usage":85.17},{"name":"Raboot","usage":78.359},{"name":"Piloswine","usage":49.413},{"name":"Lampent","usage":39.364},{"name":"Krokorok","usage":34.717},{"name":"Metang","usage":34.717},{"name":"Ferroseed","usage":34.578},{"name":"Thwackey","usage":31.741},{"name":"Duosion","usage":16.502},{"name":"Linoone-Galar","usage":13.191},{"name":"Electabuzz","usage":11.851}],"counters":[],"lead":{"usage":7.56073,"raw":32,"rawp":2.832}},"piloswine":{"usage":39.77969,"raw":330,"avg":0.223640581056,"vc":92,"abilities":[{"name":"Thick Fat","usage":100},{"name":"Oblivious","usage":0},{"name":"Snow Cloak","usage":0}],"moves":[{"name":"Icicle Crash","usage":97.401},{"name":"Ice Shard","usage":96.815},{"name":"Stealth Rock","usage":87.253},{"name":"Earthquake","usage":66.529},{"name":"High Horsepower","usage":33.471},{"name":"Other","usage":18.531}],"items":[{"name":"Eviolite","usage":84.155},{"name":"Choice Band","usage":12.659},{"name":"Other","usage":3.185}],"spreads":[{"nature":"Adamant","evs":{"hp":252,"atk":252,"def":0,"spa":0,"spd":4,"spe":0},"usage":50.146},{"nature":"Adamant","evs":{"hp":0,"atk":252,"def":0,"spa":0,"spd":4,"spe":252},"usage":12.659},{"nature":"Adamant","evs":{"hp":252,"atk":216,"def":0,"spa":0,"spd":0,"spe":40},"usage":12.58},{"nature":"Adamant","evs":{"hp":248,"atk":76,"def":0,"spa":0,"spd":164,"spe":20},"usage":6.368},{"nature":"Adamant","evs":{"hp":152,"atk":252,"def":0,"spa":0,"spd":0,"spe":104},"usage":3.185},{"nature":"Adamant","evs":{"hp":80,"atk":252,"def":0,"spa":0,"spd":0,"spe":176},"usage":3.185},{"nature":"Other","evs":{"hp":null,"atk":null,"def":null,"spa":null,"spd":null,"spe":null},"usage":11.875}],"teammates":[{"name":"Raboot","usage":54.708},{"name":"Gurdurr","usage":54.675},{"name":"Golbat","usage":54.391},{"name":"Thwackey","usage":39.19},{"name":"Ferroseed","usage":35.122},{"name":"Electabuzz","usage":30.52},{"name":"Vullaby","usage":25.223},{"name":"Wartortle","usage":21.462},{"name":"Duosion","usage":17.76},{"name":"Clefairy","usage":16.56},{"name":"Linoone-Galar","usage":16.414}],"counters":[],"lead":{"usage":16.59417,"raw":81,"rawp":7.168}},"electabuzz":{"usage":39.69566,"raw":572,"avg":0.12337099731,"vc":84,"abilities":[{"name":"Static","usage":99.506},{"name":"Vital Spirit","usage":0.494}],"moves":[{"name":"Volt Switch","usage":99.506},{"name":"Focus Blast","usage":92.182},{"name":"Thunderbolt","usage":70.666},{"name":"Taunt","usage":67.731},{"name":"Psychic","usage":19.286},{"name":"Discharge","usage":17.127},{"name":"Toxic","usage":7.152},{"name":"Ice Punch","usage":5.338},{"name":"Wild Charge","usage":5.338},{"name":"Other","usage":15.674}],"items":[{"name":"Eviolite","usage":71.16},{"name":"Rocky Helmet","usage":17.127},{"name":"Choice Specs","usage":4.389},{"name":"Life Orb","usage":2.867},{"name":"Other","usage":4.458}],"spreads":[{"nature":"Timid","evs":{"hp":0,"atk":0,"def":0,"spa":252,"spd":4,"spe":252},"usage":69.94},{"nature":"Timid","evs":{"hp":0,"atk":0,"def":16,"spa":236,"spd":4,"spe":252},"usage":17.127},{"nature":"Jolly","evs":{"hp":0,"atk":252,"def":0,"spa":0,"spd":4,"spe":252},"usage":5.338},{"nature":"Timid","evs":{"hp":32,"atk":0,"def":8,"spa":252,"spd":0,"spe":216},"usage":4.684},{"nature":"Other","evs":{"hp":null,"atk":null,"def":null,"spa":null,"spd":null,"spe":null},"usage":2.91}],"teammates":[{"name":"Wartortle","usage":31.978},{"name":"Linoone-Galar","usage":29.323},{"name":"Golbat","usage":26.555},{"name":"Magmar","usage":23.711},{"name":"Piloswine","usage":23.33},{"name":"Ferroseed","usage":20.882},{"name":"Vullaby","usage":20.691},{"name":"Raboot","usage":19.948},{"name":"Roselia","usage":18.076},{"name":"Duosion","usage":16.491},{"name":"Corsola-Galar","usage":15.417}],"counters":[],"lead":{"usage":9.60176,"raw":68,"rawp":6.018}},"ferroseed":{"usage":28.516,"raw":388,"avg":0.118853122558,"vc":92,"abilities":[{"name":"Iron Barbs","usage":100}],"moves":[{"name":"Knock Off","usage":92.073},{"name":"Stealth Rock","usage":73.424},{"name":"Gyro Ball","usage":73.415},{"name":"Spikes","usage":65.06},{"name":"Leech Seed","usage":64.134},{"name":"Bullet Seed","usage":22.289},{"name":"Other","usage":9.604}],"items":[{"name":"Eviolite","usage":96.165},{"name":"Other","usage":3.835}],"spreads":[{"nature":"Brave","evs":{"hp":252,"atk":252,"def":0,"spa":0,"spd":4,"spe":0},"usage":35.585},{"nature":"Sassy","evs":{"hp":252,"atk":4,"def":0,"spa":0,"spd":252,"spe":0},"usage":25.597},{"nature":"Sassy","evs":{"hp":252,"atk":0,"def":4,"spa":0,"spd":252,"spe":0},"usage":25.47},{"nature":"Relaxed","evs":{"hp":252,"atk":4,"def":252,"spa":0,"spd":0,"spe":0},"usage":8.772},{"nature":"Other","evs":{"hp":null,"atk":null,"def":null,"spa":null,"spd":null,"spe":null},"usage":4.576}],"teammates":[{"name":"Golbat","usage":54.981},{"name":"Raboot","usage":51.801},{"name":"Gurdurr","usage":38.765},{"name":"Thwackey","usage":37.222},{"name":"Piloswine","usage":35.585},{"name":"Electabuzz","usage":27.679},{"name":"Linoone-Galar","usage":23.571},{"name":"Duosion","usage":16.94},{"name":"Hattrem","usage":8.772},{"name":"Dusclops","usage":6.249},{"name":"Torracat","usage":5.636}],"counters":[],"lead":{"usage":4.77752,"raw":79,"rawp":6.991}},"wartortle":{"usage":27.15947,"raw":347,"avg":0.148361209413,"vc":86,"abilities":[{"name":"Torrent","usage":95.338},{"name":"Rain Dish","usage":4.662}],"moves":[{"name":"Ice Beam","usage":65.21},{"name":"Shell Smash","usage":65.21},{"name":"Surf","usage":64.074},{"name":"Rapid Spin","usage":56.706},{"name":"Flip Turn","usage":48.709},{"name":"Toxic","usage":30.279},{"name":"Seismic Toss","usage":27.629},{"name":"Weather Ball","usage":17.618},{"name":"Substitute","usage":10.526},{"name":"Other","usage":14.04}],"items":[{"name":"Eviolite","usage":99.883},{"name":"Other","usage":0.117}],"spreads":[{"nature":"Impish","evs":{"hp":248,"atk":0,"def":152,"spa":0,"spd":108,"spe":0},"usage":17.815},{"nature":"Modest","evs":{"hp":168,"atk":0,"def":0,"spa":248,"spd":4,"spe":88},"usage":17.618},{"nature":"Modest","evs":{"hp":0,"atk":0,"def":0,"spa":252,"spd":4,"spe":252},"usage":16.047},{"nature":"Modest","evs":{"hp":176,"atk":0,"def":0,"spa":252,"spd":0,"spe":80},"usage":10.932},{"nature":"Modest","evs":{"hp":168,"atk":0,"def":0,"spa":252,"spd":0,"spe":88},"usage":10.526},{"nature":"Bold","evs":{"hp":252,"atk":0,"def":252,"spa":0,"spd":4,"spe":0},"usage":9.017},{"nature":"Other","evs":{"hp":null,"atk":null,"def":null,"spa":null,"spd":null,"spe":null},"usage":18.044}],"teammates":[{"name":"Electabuzz","usage":59.251},{"name":"Magmar","usage":30.746},{"name":"Piloswine","usage":30.398},{"name":"Vullaby","usage":29.828},{"name":"Clefairy","usage":28.013},{"name":"Roselia","usage":27.96},{"name":"Thwackey","usage":23.922},{"name":"Raboot","usage":23.425},{"name":"Ivysaur","usage":21.933},{"name":"Linoone-Galar","usage":21.401},{"name":"Hattrem","usage":20.759}],"counters":[],"lead":{"usage":0.02114,"raw":19,"rawp":1.681}},"linoonegalar":{"usage":24.0943,"raw":176,"avg":0.246373832557,"vc":80,"abilities":[{"name":"Quick Feet","usage":100},{"name":"Gluttony","usage":0},{"name":"Pickup","usage":0}],"moves":[{"name":"Parting Shot","usage":100},{"name":"Knock Off","usage":100},{"name":"Double-Edge","usage":78.338},{"name":"Protect","usage":42.386},{"name":"Thunder Wave","usage":18.891},{"name":"Switcheroo","usage":18.808},{"name":"Taunt","usage":13.346},{"name":"Rain Dance","usage":8.584},{"name":"Other","usage":19.647}],"items":[{"name":"Eviolite","usage":72.608},{"name":"Choice Band","usage":18.808},{"name":"Damp Rock","usage":8.584},{"name":"Other","usage":0}],"spreads":[{"nature":"Jolly","evs":{"hp":0,"atk":252,"def":0,"spa":0,"spd":4,"spe":252},"usage":67.846},{"nature":"Jolly","evs":{"hp":0,"atk":252,"def":4,"spa":0,"spd":0,"spe":252},"usage":18.808},{"nature":"Jolly","evs":{"hp":248,"atk":8,"def":0,"spa":0,"spd":0,"spe":252},"usage":8.584},{"nature":"Other","evs":{"hp":null,"atk":null,"def":null,"spa":null,"spd":null,"spe":null},"usage":4.762}],"teammates":[{"name":"Golbat","usage":63.104},{"name":"Electabuzz","usage":57.351},{"name":"Duosion","usage":53.173},{"name":"Raboot","usage":52.845},{"name":"Ferroseed","usage":34.781},{"name":"Piloswine","usage":24.54},{"name":"Wartortle","usage":22.59},{"name":"Gurdurr","usage":21.822},{"name":"Thwackey","usage":10.822},{"name":"Combusken","usage":10.259},{"name":"Hattrem","usage":10.175}],"counters":[],"lead":{"usage":6.13969,"raw":38,"rawp":3.363}},"thwackey":{"usage":22.80489,"raw":173,"avg":0.205186947914,"vc":92,"abilities":[{"name":"Grassy Surge","usage":100}],"moves":[{"name":"Grassy Glide","usage":100},{"name":"Knock Off","usage":99.556},{"name":"Swords Dance","usage":91.117},{"name":"Drain Punch","usage":74.019},{"name":"U-turn","usage":28.847},{"name":"Other","usage":6.461}],"items":[{"name":"Eviolite","usage":96.546},{"name":"Other","usage":3.454}],"spreads":[{"nature":"Adamant","evs":{"hp":0,"atk":252,"def":0,"spa":0,"spd":4,"spe":252},"usage":63.442},{"nature":"Adamant","evs":{"hp":168,"atk":252,"def":0,"spa":0,"spd":0,"spe":88},"usage":13.187},{"nature":"Jolly","evs":{"hp":0,"atk":252,"def":0,"spa":0,"spd":4,"spe":252},"usage":11.846},{"nature":"Adamant","evs":{"hp":104,"atk":252,"def":0,"spa":0,"spd":0,"spe":152},"usage":5.652},{"nature":"Adamant","evs":{"hp":0,"atk":252,"def":4,"spa":0,"spd":0,"spe":252},"usage":5.652},{"nature":"Other","evs":{"hp":null,"atk":null,"def":null,"spa":null,"spd":null,"spe":null},"usage":0.222}],"teammates":[{"name":"Golbat","usage":70.931},{"name":"Piloswine","usage":69.536},{"name":"Ferroseed","usage":65.183},{"name":"Raboot","usage":62.683},{"name":"Gurdurr","usage":62.317},{"name":"Wartortle","usage":29.968},{"name":"Magmar","usage":21.652},{"name":"Electabuzz","usage":17.125},{"name":"Vullaby","usage":14.577},{"name":"Linoone-Galar","usage":12.843},{"name":"Clefairy","usage":11.304}],"counters":[],"lead":{"usage":1.13893,"raw":21,"rawp":1.858}},"lampent":{"usage":20.70677,"raw":69,"avg":0.43381287526,"vc":81,"abilities":[{"name":"Flash Fire","usage":100},{"name":"Flame Body","usage":0},{"name":"Infiltrator","usage":0}],"moves":[{"name":"Calm Mind","usage":100},{"name":"Substitute","usage":90.948},{"name":"Flamethrower","usage":90.948},{"name":"Energy Ball","usage":71.2},{"name":"Shadow Ball","usage":28.8},{"name":"Other","usage":18.103}],"items":[{"name":"Life Orb","usage":71.2},{"name":"Eviolite","usage":19.748},{"name":"Choice Scarf","usage":9.052},{"name":"Other","usage":0}],"spreads":[{"nature":"Timid","evs":{"hp":0,"atk":0,"def":0,"spa":252,"spd":4,"spe":252},"usage":80.252},{"nature":"Timid","evs":{"hp":0,"atk":0,"def":4,"spa":252,"spd":0,"spe":252},"usage":14.718},{"nature":"Modest","evs":{"hp":0,"atk":0,"def":4,"spa":252,"spd":0,"spe":252},"usage":5.031},{"nature":"Other","evs":{"hp":null,"atk":null,"def":null,"spa":null,"spd":null,"spe":null},"usage":0}],"teammates":[{"name":"Gurdurr","usage":76.673},{"name":"Krokorok","usage":67.622},{"name":"Metang","usage":67.622},{"name":"Golbat","usage":67.622},{"name":"Raboot","usage":67.622},{"name":"Piloswine","usage":15.074},{"name":"Fraxure","usage":15.074},{"name":"Rufflet","usage":9.571},{"name":"Charjabug","usage":9.571},{"name":"Hattrem","usage":9.571},{"name":"Duosion","usage":5.503}],"counters":[],"lead":{"usage":1.23361,"raw":6,"rawp":0.531}},"duosion":{"usage":18.73716,"raw":324,"avg":0.099278511898,"vc":81,"abilities":[{"name":"Regenerator","usage":62.468},{"name":"Magic Guard","usage":37.532},{"name":"Overcoat","usage":0}],"moves":[{"name":"Recover","usage":99.496},{"name":"Future Sight","usage":62.898},{"name":"Shadow Ball","usage":59.757},{"name":"Acid Armor","usage":36.598},{"name":"Stored Power","usage":36.598},{"name":"Calm Mind","usage":36.598},{"name":"Psychic","usage":35.743},{"name":"Toxic","usage":21.046},{"name":"Other","usage":11.266}],"items":[{"name":"Eviolite","usage":69.009},{"name":"Life Orb","usage":30.991},{"name":"Other","usage":0}],"spreads":[{"nature":"Calm","evs":{"hp":248,"atk":0,"def":0,"spa":0,"spd":252,"spe":8},"usage":34.809},{"nature":"Modest","evs":{"hp":248,"atk":0,"def":0,"spa":252,"spd":4,"spe":4},"usage":30.991},{"nature":"Calm","evs":{"hp":252,"atk":0,"def":0,"spa":0,"spd":244,"spe":12},"usage":17.401},{"nature":"Bold","evs":{"hp":252,"atk":0,"def":252,"spa":4,"spd":0,"spe":0},"usage":5.606},{"nature":"Modest","evs":{"hp":252,"atk":0,"def":44,"spa":16,"spd":188,"spe":8},"usage":4.324},{"nature":"Calm","evs":{"hp":252,"atk":0,"def":0,"spa":4,"spd":252,"spe":0},"usage":3.645},{"nature":"Other","evs":{"hp":null,"atk":null,"def":null,"spa":null,"spd":null,"spe":null},"usage":3.223}],"teammates":[{"name":"Golbat","usage":54.867},{"name":"Linoone-Galar","usage":49.194},{"name":"Raboot","usage":44.401},{"name":"Electabuzz","usage":29.841},{"name":"Gurdurr","usage":25.257},{"name":"Piloswine","usage":24.565},{"name":"Ferroseed","usage":23.126},{"name":"Marshtomp","usage":7.594},{"name":"Combusken","usage":5.606},{"name":"Wartortle","usage":5.606},{"name":"Thwackey","usage":5.606}],"counters":[],"lead":{"usage":0.61726,"raw":14,"rawp":1.239}},"magmar":{"usage":18.42294,"raw":240,"avg":0.157947893764,"vc":86,"abilities":[{"name":"Flame Body","usage":65.698},{"name":"Vital Spirit","usage":34.302}],"moves":[{"name":"Psychic","usage":49.863},{"name":"Lava Plume","usage":40.19},{"name":"Fire Blast","usage":36.146},{"name":"Flare Blitz","usage":35.205},{"name":"Mach Punch","usage":35.205},{"name":"Belly Drum","usage":35.205},{"name":"Thunder Punch","usage":35.205},{"name":"Flamethrower","usage":24.605},{"name":"Overheat","usage":21.951},{"name":"Focus Blast","usage":21.951},{"name":"Thief","usage":16.013},{"name":"Toxic","usage":15.288},{"name":"Taunt","usage":13.46},{"name":"Other","usage":19.71}],"items":[{"name":"Choice Specs","usage":51.335},{"name":"Sitrus Berry","usage":35.205},{"name":"Heavy-Duty Boots","usage":13.46},{"name":"Other","usage":0}],"spreads":[{"nature":"Modest","evs":{"hp":0,"atk":0,"def":0,"spa":252,"spd":4,"spe":252},"usage":35.578},{"nature":"Adamant","evs":{"hp":84,"atk":252,"def":0,"spa":0,"spd":0,"spe":172},"usage":27.438},{"nature":"Modest","evs":{"hp":0,"atk":4,"def":0,"spa":252,"spd":0,"spe":252},"usage":16.013},{"nature":"Timid","evs":{"hp":0,"atk":0,"def":0,"spa":252,"spd":4,"spe":252},"usage":13.204},{"nature":"Jolly","evs":{"hp":0,"atk":252,"def":4,"spa":0,"spd":0,"spe":252},"usage":6.863},{"nature":"Other","evs":{"hp":null,"atk":null,"def":null,"spa":null,"spd":null,"spe":null},"usage":0.904}],"teammates":[{"name":"Electabuzz","usage":66.834},{"name":"Corsola-Galar","usage":53.994},{"name":"Wartortle","usage":46.773},{"name":"Golbat","usage":35.221},{"name":"Vullaby","usage":31.423},{"name":"Thwackey","usage":26.293},{"name":"Piloswine","usage":22.313},{"name":"Lickitung","usage":20.223},{"name":"Pupitar","usage":20.223},{"name":"Gurdurr","usage":19.967},{"name":"Clefairy","usage":13.727}],"counters":[],"lead":{"usage":0,"raw":22,"rawp":1.947}},"metang":{"usage":17.54398,"raw":101,"avg":0.239178878897,"vc":82,"abilities":[{"name":"Clear Body","usage":100},{"name":"Light Metal","usage":0}],"moves":[{"name":"Earthquake","usage":100},{"name":"Stealth Rock","usage":97.187},{"name":"Zen Headbutt","usage":95.183},{"name":"Toxic","usage":92.89},{"name":"Other","usage":14.74}],"items":[{"name":"Eviolite","usage":92.89},{"name":"Heat Rock","usage":4.297},{"name":"Other","usage":2.813}],"spreads":[{"nature":"Careful","evs":{"hp":252,"atk":4,"def":0,"spa":0,"spd":252,"spe":0},"usage":92.89},{"nature":"Jolly","evs":{"hp":252,"atk":96,"def":0,"spa":0,"spd":0,"spe":160},"usage":4.297},{"nature":"Other","evs":{"hp":null,"atk":null,"def":null,"spa":null,"spd":null,"spe":null},"usage":2.813}],"teammates":[{"name":"Raboot","usage":90.96},{"name":"Krokorok","usage":88.222},{"name":"Lampent","usage":88.222},{"name":"Gurdurr","usage":88.222},{"name":"Golbat","usage":88.222},{"name":"Wartortle","usage":4.371},{"name":"Fraxure","usage":4.297},{"name":"Ivysaur","usage":4.297},{"name":"Charmeleon","usage":4.297},{"name":"Cutiefly","usage":4.297},{"name":"Morgrem","usage":2.367}],"counters":[],"lead":{"usage":4.61523,"raw":27,"rawp":2.389}},"krokorok":{"usage":16.52146,"raw":235,"avg":0.0974203983338,"vc":80,"abilities":[{"name":"Moxie","usage":100},{"name":"Intimidate","usage":0}],"moves":[{"name":"Knock Off","usage":100},{"name":"Earthquake","usage":100},{"name":"Crunch","usage":64.352},{"name":"Stone Edge","usage":64.352},{"name":"Power-Up Punch","usage":35.648},{"name":"Substitute","usage":35.648},{"name":"Other","usage":0}],"items":[{"name":"Choice Scarf","usage":64.352},{"name":"Leftovers","usage":35.648},{"name":"Other","usage":0}],"spreads":[{"nature":"Jolly","evs":{"hp":0,"atk":252,"def":0,"spa":0,"spd":4,"spe":252},"usage":100},{"nature":"Other","evs":{"hp":null,"atk":null,"def":null,"spa":null,"spd":null,"spe":null},"usage":0}],"teammates":[{"name":"Lampent","usage":61.118},{"name":"Metang","usage":61.118},{"name":"Raboot","usage":61.118},{"name":"Golbat","usage":61.118},{"name":"Gurdurr","usage":61.118},{"name":"Duosion","usage":1.076},{"name":"Fletchinder","usage":1.076},{"name":"Ferroseed","usage":1.076},{"name":"Corsola-Galar","usage":1.076},{"name":"Electabuzz","usage":1.076}],"counters":[],"lead":{"usage":1.24972,"raw":19,"rawp":1.681}},"corsolagalar":{"usage":14.16693,"raw":443,"avg":0.0660679827159,"vc":83,"abilities":[{"name":"Cursed Body","usage":90.339},{"name":"Weak Armor","usage":9.661}],"moves":[{"name":"Strength Sap","usage":100},{"name":"Night Shade","usage":83.368},{"name":"Whirlpool","usage":62.574},{"name":"Stealth Rock","usage":61.22},{"name":"Will-O-Wisp","usage":23.389},{"name":"Calm Mind","usage":16.355},{"name":"Shadow Ball","usage":16.355},{"name":"Ice Beam","usage":15.391},{"name":"Destiny Bond","usage":11.06},{"name":"Other","usage":10.287}],"items":[{"name":"Eviolite","usage":90.597},{"name":"Nothing","usage":9.403},{"name":"Other","usage":0}],"spreads":[{"nature":"Bold","evs":{"hp":252,"atk":0,"def":252,"spa":0,"spd":4,"spe":0},"usage":41.479},{"nature":"Calm","evs":{"hp":252,"atk":0,"def":4,"spa":0,"spd":252,"spe":0},"usage":16.135},{"nature":"Modest","evs":{"hp":252,"atk":0,"def":4,"spa":252,"spd":0,"spe":0},"usage":15.391},{"nature":"Relaxed","evs":{"hp":252,"atk":0,"def":252,"spa":0,"spd":4,"spe":0},"usage":10.439},{"nature":"Calm","evs":{"hp":248,"atk":0,"def":4,"spa":0,"spd":252,"spe":4},"usage":10.049},{"nature":"Bold","evs":{"hp":248,"atk":0,"def":160,"spa":0,"spd":100,"spe":0},"usage":5.213},{"nature":"Other","evs":{"hp":null,"atk":null,"def":null,"spa":null,"spd":null,"spe":null},"usage":1.294}],"teammates":[{"name":"Magmar","usage":41.092},{"name":"Electabuzz","usage":33.072},{"name":"Golbat","usage":24.949},{"name":"Lickitung","usage":15.391},{"name":"Pupitar","usage":15.391},{"name":"Gurdurr","usage":11.013},{"name":"Togetic","usage":10.644},{"name":"Wartortle","usage":10.492},{"name":"Roselia","usage":10.439},{"name":"Dottler","usage":10.214},{"name":"Combusken","usage":9.806}],"counters":[],"lead":{"usage":3.98371,"raw":49,"rawp":4.336}},"vullaby":{"usage":13.65163,"raw":145,"avg":0.185202791125,"vc":86,"abilities":[{"name":"Overcoat","usage":100},{"name":"Big Pecks","usage":0},{"name":"Weak Armor","usage":0}],"moves":[{"name":"Knock Off","usage":100},{"name":"Defog","usage":100},{"name":"Roost","usage":100},{"name":"U-turn","usage":72.906},{"name":"Brave Bird","usage":19.632},{"name":"Other","usage":7.462}],"items":[{"name":"Eviolite","usage":100},{"name":"Other","usage":0}],"spreads":[{"nature":"Impish","evs":{"hp":248,"atk":0,"def":164,"spa":0,"spd":0,"spe":96},"usage":69.679},{"nature":"Careful","evs":{"hp":248,"atk":0,"def":8,"spa":0,"spd":252,"spe":0},"usage":12.958},{"nature":"Careful","evs":{"hp":252,"atk":0,"def":4,"spa":0,"spd":252,"spe":0},"usage":8.414},{"nature":"Careful","evs":{"hp":252,"atk":0,"def":128,"spa":0,"spd":128,"spe":0},"usage":7.462},{"nature":"Other","evs":{"hp":null,"atk":null,"def":null,"spa":null,"spd":null,"spe":null},"usage":1.486}],"teammates":[{"name":"Electabuzz","usage":71.499},{"name":"Piloswine","usage":66.626},{"name":"Wartortle","usage":55.629},{"name":"Clefairy","usage":41.64},{"name":"Magmar","usage":38.524},{"name":"Roselia","usage":33.225},{"name":"Mareanie","usage":22.231},{"name":"Tangela","usage":21.998},{"name":"Thwackey","usage":21.702},{"name":"Koffing","usage":13.287},{"name":"Corsola-Galar","usage":8.398}],"counters":[],"lead":{"usage":1.34629,"raw":20,"rawp":1.77}},"hattrem":{"usage":12.71154,"raw":153,"avg":0.144692978752,"vc":79,"abilities":[{"name":"Magic Bounce","usage":100}],"moves":[{"name":"Psychic","usage":100},{"name":"Giga Drain","usage":63.992},{"name":"Healing Wish","usage":50.205},{"name":"Mystical Fire","usage":41.015},{"name":"Dazzling Gleam","usage":37.593},{"name":"Nuzzle","usage":32.897},{"name":"Sleep Talk","usage":25.577},{"name":"Rest","usage":25.577},{"name":"Calm Mind","usage":13.787},{"name":"Other","usage":9.358}],"items":[{"name":"Eviolite","usage":100},{"name":"Other","usage":0}],"spreads":[{"nature":"Modest","evs":{"hp":252,"atk":0,"def":48,"spa":196,"spd":0,"spe":12},"usage":50.205},{"nature":"Modest","evs":{"hp":252,"atk":0,"def":0,"spa":252,"spd":4,"spe":0},"usage":41.008},{"nature":"Bold","evs":{"hp":252,"atk":0,"def":252,"spa":0,"spd":4,"spe":0},"usage":6.871},{"nature":"Other","evs":{"hp":null,"atk":null,"def":null,"spa":null,"spd":null,"spe":null},"usage":1.916}],"teammates":[{"name":"Torracat","usage":43.282},{"name":"Wartortle","usage":35.239},{"name":"Raboot","usage":30.103},{"name":"Ivysaur","usage":29.908},{"name":"Gabite","usage":29.908},{"name":"Ferroseed","usage":20.816},{"name":"Electabuzz","usage":19.779},{"name":"Linoone-Galar","usage":16.363},{"name":"Piloswine","usage":15.184},{"name":"Dusclops","usage":14.361},{"name":"Rufflet","usage":13.073}],"counters":[],"lead":{"usage":0,"raw":9,"rawp":0.796}},"roselia":{"usage":10.41298,"raw":115,"avg":0.151362744482,"vc":83,"abilities":[{"name":"Poison Point","usage":75.62},{"name":"Natural Cure","usage":24.38}],"moves":[{"name":"Sludge Bomb","usage":100},{"name":"Synthesis","usage":75.62},{"name":"Spikes","usage":51.234},{"name":"Stun Spore","usage":48.182},{"name":"Toxic Spikes","usage":48.022},{"name":"Leaf Storm","usage":48.022},{"name":"Extrasensory","usage":23.636},{"name":"Other","usage":5.284}],"items":[{"name":"Eviolite","usage":99.256},{"name":"Other","usage":0.744}],"spreads":[{"nature":"Timid","evs":{"hp":252,"atk":0,"def":184,"spa":0,"spd":0,"spe":72},"usage":48.182},{"nature":"Calm","evs":{"hp":248,"atk":0,"def":8,"spa":0,"spd":252,"spe":0},"usage":24.386},{"nature":"Modest","evs":{"hp":4,"atk":0,"def":0,"spa":252,"spd":0,"spe":252},"usage":23.636},{"nature":"Other","evs":{"hp":null,"atk":null,"def":null,"spa":null,"spd":null,"spe":null},"usage":3.796}],"teammates":[{"name":"Electabuzz","usage":90.581},{"name":"Wartortle","usage":75.62},{"name":"Piloswine","usage":51.234},{"name":"Clefairy","usage":51.234},{"name":"Vullaby","usage":48.182},{"name":"Magmar","usage":24.386},{"name":"Togetic","usage":24.386},{"name":"Corsola-Galar","usage":24.386},{"name":"Morgrem","usage":18.013},{"name":"Dragonair","usage":18.013},{"name":"Nuzleaf","usage":18.013}],"counters":[],"lead":{"usage":0.4477,"raw":14,"rawp":1.239}},"clefairy":{"usage":8.60754,"raw":176,"avg":0.0693103178911,"vc":86,"abilities":[{"name":"Magic Guard","usage":99.841},{"name":"Cute Charm","usage":0.159},{"name":"Friend Guard","usage":0}],"moves":[{"name":"Soft-Boiled","usage":81.314},{"name":"Moonblast","usage":81.314},{"name":"Stealth Rock","usage":80.287},{"name":"Covet","usage":65.673},{"name":"Teleport","usage":18.527},{"name":"Wish","usage":18.527},{"name":"Thunder Wave","usage":15.641},{"name":"Seismic Toss","usage":15.641},{"name":"Trick","usage":15.641},{"name":"Other","usage":7.435}],"items":[{"name":"Eviolite","usage":97.113},{"name":"Other","usage":2.887}],"spreads":[{"nature":"Bold","evs":{"hp":248,"atk":0,"def":240,"spa":0,"spd":0,"spe":20},"usage":61.76},{"nature":"Bold","evs":{"hp":252,"atk":0,"def":156,"spa":0,"spd":76,"spe":24},"usage":15.641},{"nature":"Sassy","evs":{"hp":252,"atk":0,"def":0,"spa":4,"spd":252,"spe":0},"usage":15.64},{"nature":"Relaxed","evs":{"hp":252,"atk":0,"def":252,"spa":0,"spd":4,"spe":0},"usage":3.913},{"nature":"Other","evs":{"hp":null,"atk":null,"def":null,"spa":null,"spd":null,"spe":null},"usage":3.046}],"teammates":[{"name":"Wartortle","usage":97.113},{"name":"Piloswine","usage":81.314},{"name":"Vullaby","usage":77.401},{"name":"Electabuzz","usage":77.401},{"name":"Roselia","usage":65.673},{"name":"Thwackey","usage":31.281},{"name":"Magmar","usage":31.281},{"name":"Linoone-Galar","usage":15.64},{"name":"Linoone-Galar","usage":15.64}],"counters":[],"lead":{"usage":0,"raw":27,"rawp":2.389}},"torracat":{"usage":7.66104,"raw":95,"avg":0.131066722345,"vc":77,"abilities":[{"name":"Intimidate","usage":100},{"name":"Blaze","usage":0}],"moves":[{"name":"Parting Shot","usage":75.444},{"name":"Toxic","usage":52.132},{"name":"Overheat","usage":52.132},{"name":"Sunny Day","usage":52.132},{"name":"Fake Out","usage":24.033},{"name":"Will-O-Wisp","usage":24.033},{"name":"Flame Charge","usage":24.033},{"name":"Fire Fang","usage":24.033},{"name":"Flare Blitz","usage":23.835},{"name":"Outrage","usage":23.835},{"name":"U-turn","usage":23.312},{"name":"Other","usage":1.046}],"items":[{"name":"Heat Rock","usage":52.132},{"name":"Life Orb","usage":24.033},{"name":"Heavy-Duty Boots","usage":23.312},{"name":"Other","usage":0.523}],"spreads":[{"nature":"Calm","evs":{"hp":252,"atk":0,"def":116,"spa":0,"spd":140,"spe":0},"usage":52.132},{"nature":"Jolly","evs":{"hp":0,"atk":252,"def":0,"spa":0,"spd":4,"spe":252},"usage":47.868},{"nature":"Other","evs":{"hp":null,"atk":null,"def":null,"spa":null,"spd":null,"spe":null},"usage":0}],"teammates":[{"name":"Hattrem","usage":75.444},{"name":"Ivysaur","usage":52.132},{"name":"Gabite","usage":52.132},{"name":"Raboot","usage":52.132},{"name":"Wartortle","usage":52.132},{"name":"Linoone-Galar","usage":23.312},{"name":"Electabuzz","usage":23.312},{"name":"Ferroseed","usage":23.312},{"name":"Dusclops","usage":19.079},{"name":"Corsola-Galar","usage":4.756},{"name":"Fraxure","usage":0.523}],"counters":[],"lead":{"usage":1.09836,"raw":13,"rawp":1.15}},"ivysaur":{"usage":6.84613,"raw":39,"avg":0.195064561878,"vc":77,"abilities":[{"name":"Chlorophyll","usage":100},{"name":"Overgrow","usage":0}],"moves":[{"name":"Growth","usage":99.227},{"name":"Weather Ball","usage":91.972},{"name":"Solar Beam","usage":80.422},{"name":"Sludge Bomb","usage":75.004},{"name":"Giga Drain","usage":19.578},{"name":"Knock Off","usage":18.805},{"name":"Other","usage":14.992}],"items":[{"name":"Eviolite","usage":100},{"name":"Other","usage":0}],"spreads":[{"nature":"Modest","evs":{"hp":192,"atk":0,"def":0,"spa":252,"spd":0,"spe":64},"usage":87.677},{"nature":"Modest","evs":{"hp":0,"atk":0,"def":0,"spa":252,"spd":4,"spe":252},"usage":11.55},{"nature":"Other","evs":{"hp":null,"atk":null,"def":null,"spa":null,"spd":null,"spe":null},"usage":0.773}],"teammates":[{"name":"Wartortle","usage":95.598},{"name":"Raboot","usage":81.195},{"name":"Gabite","usage":76.792},{"name":"Torracat","usage":76.792},{"name":"Hattrem","usage":76.792},{"name":"Charmeleon","usage":18.805},{"name":"Fraxure","usage":11.55},{"name":"Metang","usage":11.55},{"name":"Cutiefly","usage":11.55},{"name":"Electabuzz","usage":7.255},{"name":"Dragonair","usage":7.255}],"counters":[],"lead":{"usage":0.54959,"raw":3,"rawp":0.265}},"tangela":{"usage":6.29729,"raw":177,"avg":0.0670146957585,"vc":84,"abilities":[{"name":"Regenerator","usage":100},{"name":"Chlorophyll","usage":0}],"moves":[{"name":"Sludge Bomb","usage":100},{"name":"Knock Off","usage":89.559},{"name":"Giga Drain","usage":56.753},{"name":"Sleep Powder","usage":37.049},{"name":"Stun Spore","usage":33.921},{"name":"Leaf Storm","usage":32.806},{"name":"Leech Seed","usage":18.59},{"name":"Energy Ball","usage":10.441},{"name":"Ancient Power","usage":10.441},{"name":"Other","usage":10.441}],"items":[{"name":"Eviolite","usage":89.559},{"name":"Assault Vest","usage":10.441},{"name":"Other","usage":0}],"spreads":[{"nature":"Bold","evs":{"hp":248,"atk":0,"def":252,"spa":0,"spd":0,"spe":8},"usage":20.986},{"nature":"Bold","evs":{"hp":252,"atk":0,"def":148,"spa":0,"spd":104,"spe":4},"usage":19.872},{"nature":"Calm","evs":{"hp":252,"atk":0,"def":0,"spa":0,"spd":252,"spe":4},"usage":18.59},{"nature":"Bold","evs":{"hp":252,"atk":0,"def":232,"spa":0,"spd":0,"spe":24},"usage":13.474},{"nature":"Modest","evs":{"hp":80,"atk":0,"def":0,"spa":252,"spd":0,"spe":176},"usage":12.935},{"nature":"Modest","evs":{"hp":252,"atk":0,"def":0,"spa":252,"spd":4,"spe":0},"usage":10.441},{"nature":"Other","evs":{"hp":null,"atk":null,"def":null,"spa":null,"spd":null,"spe":null},"usage":3.703}],"teammates":[{"name":"Electabuzz","usage":74.132},{"name":"Vullaby","usage":54.8},{"name":"Piloswine","usage":54.26},{"name":"Golbat","usage":46.28},{"name":"Magmar","usage":40.858},{"name":"Mareanie","usage":34.46},{"name":"Gurdurr","usage":32.806},{"name":"Duosion","usage":26.409},{"name":"Raboot","usage":20.339},{"name":"Corsola-Galar","usage":19.872},{"name":"Trubbish","usage":18.59}],"counters":[],"lead":{"usage":1.32739,"raw":19,"rawp":1.681}},"gabite":{"usage":6.16226,"raw":63,"avg":0.163037960353,"vc":77,"abilities":[{"name":"Rough Skin","usage":100},{"name":"Sand Veil","usage":0}],"moves":[{"name":"Earthquake","usage":100},{"name":"Toxic","usage":99.141},{"name":"Stealth Rock","usage":99.141},{"name":"Dragon Claw","usage":85.315},{"name":"Other","usage":16.404}],"items":[{"name":"Eviolite","usage":99.441},{"name":"Other","usage":0.559}],"spreads":[{"nature":"Jolly","evs":{"hp":248,"atk":0,"def":216,"spa":0,"spd":0,"spe":44},"usage":85.315},{"nature":"Jolly","evs":{"hp":252,"atk":0,"def":216,"spa":0,"spd":0,"spe":40},"usage":13.826},{"nature":"Other","evs":{"hp":null,"atk":null,"def":null,"spa":null,"spd":null,"spe":null},"usage":0.859}],"teammates":[{"name":"Torracat","usage":85.315},{"name":"Wartortle","usage":85.315},{"name":"Ivysaur","usage":85.315},{"name":"Hattrem","usage":85.315},{"name":"Raboot","usage":85.315},{"name":"Gurdurr","usage":14.385},{"name":"Lampent","usage":13.826},{"name":"Gothorita","usage":13.826},{"name":"Linoone-Galar","usage":13.826},{"name":"Linoone-Galar","usage":13.826}],"counters":[],"lead":{"usage":0.85201,"raw":14,"rawp":1.239}},"fraxure":{"usage":5.2578,"raw":175,"avg":0.0636855574446,"vc":81,"abilities":[{"name":"Mold Breaker","usage":100},{"name":"Unnerve","usage":0},{"name":"Rivalry","usage":0}],"moves":[{"name":"Poison Jab","usage":100},{"name":"Outrage","usage":88.054},{"name":"Superpower","usage":73.341},{"name":"Swords Dance","usage":65.327},{"name":"Dragon Claw","usage":19.96},{"name":"Dragon Dance","usage":14.713},{"name":"First Impression","usage":14.713},{"name":"Low Kick","usage":11.946},{"name":"Other","usage":11.946}],"items":[{"name":"Eviolite","usage":79.243},{"name":"Choice Band","usage":19.96},{"name":"Other","usage":0.797}],"spreads":[{"nature":"Jolly","evs":{"hp":0,"atk":252,"def":4,"spa":0,"spd":0,"spe":252},"usage":53.381},{"nature":"Adamant","evs":{"hp":0,"atk":252,"def":0,"spa":0,"spd":4,"spe":252},"usage":46.619},{"nature":"Other","evs":{"hp":null,"atk":null,"def":null,"spa":null,"spd":null,"spe":null},"usage":0}],"teammates":[{"name":"Piloswine","usage":66.686},{"name":"Lampent","usage":54.676},{"name":"Rufflet","usage":34.716},{"name":"Charjabug","usage":34.716},{"name":"Hattrem","usage":34.716},{"name":"Gurdurr","usage":31.971},{"name":"Duosion","usage":19.96},{"name":"Koffing","usage":19.96},{"name":"Electabuzz","usage":12.011},{"name":"Omanyte","usage":12.011},{"name":"Dusclops","usage":12.011}],"counters":[],"lead":{"usage":0,"raw":10,"rawp":0.885}},"combusken":{"usage":4.31455,"raw":180,"avg":0.0326148529677,"vc":73,"abilities":[{"name":"Speed Boost","usage":100},{"name":"Blaze","usage":0}],"moves":[{"name":"Brick Break","usage":99.571},{"name":"Swords Dance","usage":99.193},{"name":"Protect","usage":67.707},{"name":"Blaze Kick","usage":53.426},{"name":"Flare Blitz","usage":30.811},{"name":"Night Slash","usage":17.966},{"name":"Fire Punch","usage":15.763},{"name":"Other","usage":15.564}],"items":[{"name":"Eviolite","usage":67.534},{"name":"Life Orb","usage":30.321},{"name":"Other","usage":2.145}],"spreads":[{"nature":"Jolly","evs":{"hp":0,"atk":252,"def":0,"spa":0,"spd":4,"spe":252},"usage":51.883},{"nature":"Adamant","evs":{"hp":0,"atk":252,"def":0,"spa":0,"spd":4,"spe":252},"usage":46.574},{"nature":"Other","evs":{"hp":null,"atk":null,"def":null,"spa":null,"spd":null,"spe":null},"usage":1.544}],"teammates":[{"name":"Linoone-Galar","usage":67.217},{"name":"Golbat","usage":67.217},{"name":"Corsola-Galar","usage":58.58},{"name":"Hattrem","usage":42.5},{"name":"Thwackey","usage":40.93},{"name":"Wartortle","usage":40.51},{"name":"Duosion","usage":39.703},{"name":"Brionne","usage":30.75},{"name":"Ferroseed","usage":30.75},{"name":"Drakloak","usage":30.321},{"name":"Electabuzz","usage":27.514}],"counters":[],"lead":{"usage":0.84668,"raw":16,"rawp":1.416}},"dusclops":{"usage":4.09218,"raw":247,"avg":0.0353942541364,"vc":73,"abilities":[{"name":"Frisk","usage":73.806},{"name":"Pressure","usage":26.194}],"moves":[{"name":"Pain Split","usage":72.963},{"name":"Toxic","usage":59.481},{"name":"Night Shade","usage":58.637},{"name":"Shadow Sneak","usage":57.433},{"name":"Will-O-Wisp","usage":41.363},{"name":"Poltergeist","usage":25.833},{"name":"Brick Break","usage":25.833},{"name":"Trick Room","usage":24.99},{"name":"Hex","usage":15.53},{"name":"Other","usage":17.938}],"items":[{"name":"Eviolite","usage":100},{"name":"Other","usage":0}],"spreads":[{"nature":"Impish","evs":{"hp":4,"atk":0,"def":252,"spa":0,"spd":252,"spe":0},"usage":57.433},{"nature":"Careful","evs":{"hp":252,"atk":0,"def":60,"spa":0,"spd":196,"spe":0},"usage":24.99},{"nature":"Calm","evs":{"hp":252,"atk":0,"def":0,"spa":4,"spd":252,"spe":0},"usage":15.53},{"nature":"Other","evs":{"hp":null,"atk":null,"def":null,"spa":null,"spd":null,"spe":null},"usage":2.048}],"teammates":[{"name":"Electabuzz","usage":75.52},{"name":"Ferroseed","usage":59.303},{"name":"Hattrem","usage":57.433},{"name":"Torracat","usage":43.773},{"name":"Linoone-Galar","usage":43.773},{"name":"Thwackey","usage":22.83},{"name":"Piloswine","usage":18.931},{"name":"Omanyte","usage":18.087},{"name":"Gurdurr","usage":18.087},{"name":"Fraxure","usage":18.087},{"name":"Drakloak","usage":15.53}],"counters":[],"lead":{"usage":0,"raw":30,"rawp":2.655}},"togetic":{"usage":4.01732,"raw":97,"avg":0.0992023039361,"vc":83,"abilities":[{"name":"Super Luck","usage":98.687},{"name":"Serene Grace","usage":1.313},{"name":"Hustle","usage":0}],"moves":[{"name":"Dazzling Gleam","usage":100},{"name":"Air Cutter","usage":88.183},{"name":"Roost","usage":77.478},{"name":"Thunder Wave","usage":66.974},{"name":"Flamethrower","usage":21.208},{"name":"Nasty Plot","usage":21.208},{"name":"Heal Bell","usage":10.504},{"name":"Other","usage":14.443}],"items":[{"name":"Eviolite","usage":100},{"name":"Other","usage":0}],"spreads":[{"nature":"Bold","evs":{"hp":248,"atk":0,"def":252,"spa":0,"spd":8,"spe":0},"usage":66.974},{"nature":"Timid","evs":{"hp":0,"atk":0,"def":4,"spa":252,"spd":0,"spe":252},"usage":21.208},{"nature":"Modest","evs":{"hp":176,"atk":0,"def":136,"spa":180,"spd":16,"spe":0},"usage":10.504},{"nature":"Other","evs":{"hp":null,"atk":null,"def":null,"spa":null,"spd":null,"spe":null},"usage":1.313}],"teammates":[{"name":"Corsola-Galar","usage":68.288},{"name":"Wartortle","usage":66.974},{"name":"Magmar","usage":66.974},{"name":"Electabuzz","usage":66.974},{"name":"Roselia","usage":66.974},{"name":"Gabite","usage":21.208},{"name":"Linoone-Galar","usage":21.208},{"name":"Lampent","usage":21.208},{"name":"Gothorita","usage":21.208},{"name":"Gurdurr","usage":21.208},{"name":"Morgrem","usage":10.504}],"counters":[],"lead":{"usage":0,"raw":6,"rawp":0.531}},"lickitung":{"usage":3.96689,"raw":12,"avg":0.419815814839,"vc":78,"abilities":[{"name":"Oblivious","usage":66.361},{"name":"Cloud Nine","usage":33.639},{"name":"Own Tempo","usage":0}],"moves":[{"name":"Protect","usage":100},{"name":"Knock Off","usage":100},{"name":"Wish","usage":100},{"name":"Body Slam","usage":100},{"name":"Other","usage":0}],"items":[{"name":"Eviolite","usage":100},{"name":"Other","usage":0}],"spreads":[{"nature":"Impish","evs":{"hp":252,"atk":4,"def":252,"spa":0,"spd":0,"spe":0},"usage":100},{"nature":"Other","evs":{"hp":null,"atk":null,"def":null,"spa":null,"spd":null,"spe":null},"usage":0}],"teammates":[{"name":"Pupitar","usage":100},{"name":"Corsola-Galar","usage":100},{"name":"Magmar","usage":100},{"name":"Golbat","usage":100},{"name":"Dottler","usage":66.361},{"name":"Lairon","usage":33.639},{"name":"Lairon","usage":33.639}],"counters":[],"lead":{"usage":0,"raw":2,"rawp":0.177}},"pupitar":{"usage":3.96689,"raw":7,"avg":0.587742140774,"vc":78,"abilities":[{"name":"Shed Skin","usage":100}],"moves":[{"name":"Rest","usage":100},{"name":"Earthquake","usage":100},{"name":"Stealth Rock","usage":100},{"name":"Smack Down","usage":100},{"name":"Other","usage":0}],"items":[{"name":"Eviolite","usage":100},{"name":"Other","usage":0}],"spreads":[{"nature":"Adamant","evs":{"hp":252,"atk":4,"def":0,"spa":0,"spd":252,"spe":0},"usage":100},{"nature":"Other","evs":{"hp":null,"atk":null,"def":null,"spa":null,"spd":null,"spe":null},"usage":0}],"teammates":[{"name":"Magmar","usage":100},{"name":"Corsola-Galar","usage":100},{"name":"Golbat","usage":100},{"name":"Lickitung","usage":100},{"name":"Dottler","usage":66.361},{"name":"Lairon","usage":33.639},{"name":"Lairon","usage":33.639}],"counters":[],"lead":{"usage":2.6582,"raw":2,"rawp":0.177}},"charjabug":{"usage":3.72632,"raw":76,"avg":0.131279498877,"vc":80,"abilities":[{"name":"Battery","usage":100}],"moves":[{"name":"Sticky Web","usage":98.346},{"name":"Volt Switch","usage":98.346},{"name":"Toxic","usage":98.346},{"name":"Skitter Smack","usage":98.346},{"name":"Other","usage":6.616}],"items":[{"name":"Eviolite","usage":98.346},{"name":"Other","usage":1.654}],"spreads":[{"nature":"Impish","evs":{"hp":252,"atk":4,"def":252,"spa":0,"spd":0,"spe":0},"usage":71.214},{"nature":"Sassy","evs":{"hp":252,"atk":0,"def":4,"spa":0,"spd":252,"spe":0},"usage":27.132},{"nature":"Other","evs":{"hp":null,"atk":null,"def":null,"spa":null,"spd":null,"spe":null},"usage":1.654}],"teammates":[{"name":"Piloswine","usage":73.445},{"name":"Rufflet","usage":46.313},{"name":"Fraxure","usage":46.313},{"name":"Lampent","usage":46.313},{"name":"Hattrem","usage":46.313},{"name":"Abra","usage":27.132},{"name":"Woobat","usage":27.132},{"name":"Swirlix","usage":27.132},{"name":"Sliggoo","usage":27.132},{"name":"Hakamo-o","usage":1.654},{"name":"Shelgon","usage":1.654}],"counters":[],"lead":{"usage":2.47296,"raw":35,"rawp":3.097}},"brionne":{"usage":3.70373,"raw":107,"avg":0.074480954964,"vc":70,"abilities":[{"name":"Torrent","usage":55.269},{"name":"Liquid Voice","usage":44.731}],"moves":[{"name":"Ice Beam","usage":100},{"name":"Surf","usage":70.009},{"name":"Flip Turn","usage":54.851},{"name":"Hydro Pump","usage":54.851},{"name":"Hyper Voice","usage":44.731},{"name":"Moonblast","usage":29.991},{"name":"Blizzard","usage":29.572},{"name":"Other","usage":15.996}],"items":[{"name":"Choice Specs","usage":84.423},{"name":"Eviolite","usage":15.159},{"name":"Other","usage":0.418}],"spreads":[{"nature":"Modest","evs":{"hp":0,"atk":0,"def":0,"spa":252,"spd":4,"spe":252},"usage":54.851},{"nature":"Modest","evs":{"hp":252,"atk":0,"def":0,"spa":252,"spd":4,"spe":0},"usage":29.572},{"nature":"Quiet","evs":{"hp":252,"atk":4,"def":0,"spa":252,"spd":0,"spe":0},"usage":15.158},{"nature":"Other","evs":{"hp":null,"atk":null,"def":null,"spa":null,"spd":null,"spe":null},"usage":0.418}],"teammates":[{"name":"Ferroseed","usage":48.483},{"name":"Linoone-Galar","usage":38.575},{"name":"Electabuzz","usage":38.575},{"name":"Wartortle","usage":38.575},{"name":"Combusken","usage":29.991},{"name":"Corsola-Galar","usage":29.991},{"name":"Hattrem","usage":29.572},{"name":"Drakloak","usage":29.572},{"name":"Lombre","usage":20.083},{"name":"Dwebble","usage":20.083},{"name":"Fletchinder","usage":18.492}],"counters":[],"lead":{"usage":0,"raw":12,"rawp":1.062}},"mareanie":{"usage":3.55694,"raw":39,"avg":0.131750776558,"vc":84,"abilities":[{"name":"Regenerator","usage":100},{"name":"Merciless","usage":0}],"moves":[{"name":"Knock Off","usage":100},{"name":"Toxic Spikes","usage":100},{"name":"Recover","usage":100},{"name":"Haze","usage":75.67},{"name":"Scald","usage":24.33},{"name":"Other","usage":0}],"items":[{"name":"Eviolite","usage":100},{"name":"Other","usage":0}],"spreads":[{"nature":"Calm","evs":{"hp":252,"atk":0,"def":4,"spa":0,"spd":252,"spe":0},"usage":37.895},{"nature":"Careful","evs":{"hp":252,"atk":0,"def":4,"spa":0,"spd":252,"spe":0},"usage":37.775},{"nature":"Bold","evs":{"hp":252,"atk":0,"def":252,"spa":0,"spd":4,"spe":0},"usage":24.33},{"nature":"Other","evs":{"hp":null,"atk":null,"def":null,"spa":null,"spd":null,"spe":null},"usage":0}],"teammates":[{"name":"Vullaby","usage":100},{"name":"Piloswine","usage":75.67},{"name":"Electabuzz","usage":75.67},{"name":"Magmar","usage":75.67},{"name":"Tangela","usage":62.225},{"name":"Corsola-Galar","usage":37.775},{"name":"Duosion","usage":24.33},{"name":"Golbat","usage":24.33},{"name":"Golbat","usage":24.33}],"counters":[],"lead":{"usage":0,"raw":6,"rawp":0.531}},"koffing":{"usage":3.44723,"raw":44,"avg":0.173986427301,"vc":81,"abilities":[{"name":"Neutralizing Gas","usage":100},{"name":"Levitate","usage":0}],"moves":[{"name":"Toxic Spikes","usage":100},{"name":"Thief","usage":100},{"name":"Pain Split","usage":100},{"name":"Sludge Bomb","usage":70.391},{"name":"Will-O-Wisp","usage":29.609},{"name":"Other","usage":0}],"items":[{"name":"Eviolite","usage":100}],"spreads":[{"nature":"Relaxed","evs":{"hp":248,"atk":0,"def":140,"spa":0,"spd":108,"spe":12},"usage":70.391},{"nature":"Relaxed","evs":{"hp":248,"atk":8,"def":252,"spa":0,"spd":0,"spe":0},"usage":29.609},{"nature":"Other","evs":{"hp":null,"atk":null,"def":null,"spa":null,"spd":null,"spe":null},"usage":0}],"teammates":[{"name":"Wartortle","usage":47.643},{"name":"Magmar","usage":47.643},{"name":"Electabuzz","usage":47.643},{"name":"Thwackey","usage":47.643},{"name":"Vullaby","usage":47.643},{"name":"Duosion","usage":29.609},{"name":"Piloswine","usage":29.609},{"name":"Fraxure","usage":29.609},{"name":"Gurdurr","usage":29.609},{"name":"Lampent","usage":29.609}],"counters":[],"lead":{"usage":0,"raw":5,"rawp":0.442}},"dragonair":{"usage":3.15473,"raw":102,"avg":0.0548354517008,"vc":70,"abilities":[{"name":"Shed Skin","usage":100},{"name":"Marvel Scale","usage":0}],"moves":[{"name":"Dragon Dance","usage":86.843},{"name":"Outrage","usage":86.843},{"name":"Rest","usage":69.08},{"name":"Waterfall","usage":55.47},{"name":"Extreme Speed","usage":31.373},{"name":"Iron Tail","usage":17.763},{"name":"Wrap","usage":13.157},{"name":"Toxic","usage":13.157},{"name":"Protect","usage":13.157},{"name":"Other","usage":13.157}],"items":[{"name":"Eviolite","usage":100},{"name":"Other","usage":0}],"spreads":[{"nature":"Careful","evs":{"hp":4,"atk":0,"def":252,"spa":0,"spd":252,"spe":0},"usage":69.08},{"nature":"Adamant","evs":{"hp":0,"atk":252,"def":0,"spa":0,"spd":4,"spe":252},"usage":17.763},{"nature":"Careful","evs":{"hp":252,"atk":0,"def":4,"spa":0,"spd":252,"spe":0},"usage":13.157},{"nature":"Other","evs":{"hp":null,"atk":null,"def":null,"spa":null,"spd":null,"spe":null},"usage":0}],"teammates":[{"name":"Electabuzz","usage":65.804},{"name":"Morgrem","usage":52.648},{"name":"Nuzleaf","usage":52.648},{"name":"Carkol","usage":52.648},{"name":"Roselia","usage":52.648},{"name":"Brionne","usage":17.763},{"name":"Tangela","usage":17.763},{"name":"Klang","usage":17.763},{"name":"Seadra","usage":17.763},{"name":"Dartrix","usage":17.763},{"name":"Ivysaur","usage":13.157}],"counters":[],"lead":{"usage":0.67057,"raw":11,"rawp":0.973}},"klang":{"usage":2.66684,"raw":65,"avg":0.0617380435855,"vc":81,"abilities":[{"name":"Clear Body","usage":100},{"name":"Plus","usage":0},{"name":"Minus","usage":0}],"moves":[{"name":"Shift Gear","usage":100},{"name":"Gear Grind","usage":100},{"name":"Wild Charge","usage":100},{"name":"Volt Switch","usage":49.258},{"name":"Assurance","usage":25.597},{"name":"Facade","usage":25.145},{"name":"Other","usage":0}],"items":[{"name":"Leftovers","usage":50.742},{"name":"Eviolite","usage":49.258},{"name":"Other","usage":0}],"spreads":[{"nature":"Adamant","evs":{"hp":112,"atk":252,"def":0,"spa":0,"spd":0,"spe":144},"usage":49.258},{"nature":"Adamant","evs":{"hp":0,"atk":252,"def":0,"spa":0,"spd":4,"spe":252},"usage":25.597},{"nature":"Adamant","evs":{"hp":252,"atk":252,"def":0,"spa":0,"spd":4,"spe":0},"usage":25.145},{"nature":"Other","evs":{"hp":null,"atk":null,"def":null,"spa":null,"spd":null,"spe":null},"usage":0}],"teammates":[{"name":"Electabuzz","usage":49.258},{"name":"Zweilous","usage":49.258},{"name":"Gurdurr","usage":49.258},{"name":"Corsola-Galar","usage":49.258},{"name":"Magmar","usage":49.258},{"name":"Scraggy","usage":25.597},{"name":"Ferroseed","usage":25.597},{"name":"Thwackey","usage":25.597},{"name":"Dusclops","usage":25.597},{"name":"Drakloak","usage":25.597},{"name":"Brionne","usage":25.145}],"counters":[],"lead":{"usage":0,"raw":2,"rawp":0.177}},"dottler":{"usage":2.63332,"raw":34,"avg":0.16256580602,"vc":77,"abilities":[{"name":"Swarm","usage":100},{"name":"Compound Eyes","usage":0}],"moves":[{"name":"Recover","usage":100},{"name":"Psychic","usage":99.968},{"name":"Body Press","usage":99.968},{"name":"Bug Buzz","usage":99.968},{"name":"Other","usage":0.097}],"items":[{"name":"Eviolite","usage":99.968},{"name":"Other","usage":0.032}],"spreads":[{"nature":"Bold","evs":{"hp":252,"atk":0,"def":252,"spa":4,"spd":0,"spe":0},"usage":99.968},{"nature":"Other","evs":{"hp":null,"atk":null,"def":null,"spa":null,"spd":null,"spe":null},"usage":0.032}],"teammates":[{"name":"Lickitung","usage":99.968},{"name":"Pupitar","usage":99.968},{"name":"Corsola-Galar","usage":99.968},{"name":"Magmar","usage":99.968},{"name":"Golbat","usage":99.968},{"name":"Golbat","usage":99.968}],"counters":[],"lead":{"usage":1.30869,"raw":11,"rawp":0.973}},"morgrem":{"usage":2.5401,"raw":76,"avg":0.0508974790924,"vc":61,"abilities":[{"name":"Pickpocket","usage":82.515},{"name":"Prankster","usage":17.485},{"name":"Frisk","usage":0}],"moves":[{"name":"Dark Pulse","usage":86.648},{"name":"Dazzling Gleam","usage":86.648},{"name":"Nasty Plot","usage":82.947},{"name":"Burning Jealousy","usage":82.515},{"name":"Thunder Wave","usage":17.053},{"name":"Foul Play","usage":13.352},{"name":"Reflect","usage":13.352},{"name":"Other","usage":17.485}],"items":[{"name":"Eviolite","usage":86.648},{"name":"Light Clay","usage":13.352},{"name":"Other","usage":0}],"spreads":[{"nature":"Timid","evs":{"hp":0,"atk":8,"def":0,"spa":248,"spd":0,"spe":252},"usage":82.515},{"nature":"Impish","evs":{"hp":156,"atk":64,"def":152,"spa":0,"spd":136,"spe":0},"usage":13.352},{"nature":"Other","evs":{"hp":null,"atk":null,"def":null,"spa":null,"spd":null,"spe":null},"usage":4.133}],"teammates":[{"name":"Dragonair","usage":62.886},{"name":"Nuzleaf","usage":62.886},{"name":"Electabuzz","usage":62.886},{"name":"Carkol","usage":62.886},{"name":"Roselia","usage":62.886},{"name":"Metang","usage":13.785},{"name":"Gastly","usage":13.352},{"name":"Raboot","usage":13.352},{"name":"Togetic","usage":13.352},{"name":"Palpitoad","usage":13.352},{"name":"Duosion","usage":3.701}],"counters":[],"lead":{"usage":0,"raw":26,"rawp":2.301}},"rufflet":{"usage":2.41496,"raw":24,"avg":0.159079911691,"vc":79,"abilities":[{"name":"Hustle","usage":96.796},{"name":"Sheer Force","usage":3.204}],"moves":[{"name":"U-turn","usage":100},{"name":"Close Combat","usage":100},{"name":"Brave Bird","usage":96.796},{"name":"Aerial Ace","usage":96.796},{"name":"Other","usage":6.408}],"items":[{"name":"Choice Band","usage":96.796},{"name":"Other","usage":3.204}],"spreads":[{"nature":"Adamant","evs":{"hp":0,"atk":252,"def":4,"spa":0,"spd":0,"spe":252},"usage":96.796},{"nature":"Other","evs":{"hp":null,"atk":null,"def":null,"spa":null,"spd":null,"spe":null},"usage":3.204}],"teammates":[{"name":"Piloswine","usage":62.949},{"name":"Fraxure","usage":62.949},{"name":"Lampent","usage":62.949},{"name":"Charjabug","usage":62.949},{"name":"Hattrem","usage":62.949},{"name":"Morgrem","usage":3.204},{"name":"Duosion","usage":3.204},{"name":"Ferroseed","usage":3.204},{"name":"Tentacool","usage":3.204},{"name":"Marshtomp","usage":3.204}],"counters":[],"lead":{"usage":0,"raw":1,"rawp":0.088}},"marshtomp":{"usage":2.3416,"raw":84,"avg":0.097387214999,"vc":79,"abilities":[{"name":"Torrent","usage":100},{"name":"Damp","usage":0}],"moves":[{"name":"Stealth Rock","usage":99.404},{"name":"Earthquake","usage":75.618},{"name":"Rest","usage":62.08},{"name":"Sleep Talk","usage":62.08},{"name":"Scald","usage":61.706},{"name":"Toxic","usage":34.029},{"name":"Other","usage":5.082}],"items":[{"name":"Eviolite","usage":99.404},{"name":"Other","usage":0.596}],"spreads":[{"nature":"Careful","evs":{"hp":248,"atk":0,"def":120,"spa":0,"spd":140,"spe":0},"usage":37.699},{"nature":"Careful","evs":{"hp":252,"atk":4,"def":0,"spa":0,"spd":252,"spe":0},"usage":34.029},{"nature":"Calm","evs":{"hp":252,"atk":0,"def":84,"spa":0,"spd":172,"spe":0},"usage":24.382},{"nature":"Other","evs":{"hp":null,"atk":null,"def":null,"spa":null,"spd":null,"spe":null},"usage":3.891}],"teammates":[{"name":"Duosion","usage":65.376},{"name":"Golbat","usage":62.08},{"name":"Linoone-Galar","usage":37.699},{"name":"Electabuzz","usage":37.699},{"name":"Raboot","usage":37.699},{"name":"Tangela","usage":24.382},{"name":"Vullaby","usage":24.382},{"name":"Mareanie","usage":24.382},{"name":"Morgrem","usage":3.295},{"name":"Rufflet","usage":3.295},{"name":"Ferroseed","usage":3.295}],"counters":[],"lead":{"usage":0,"raw":15,"rawp":1.327}},"drakloak":{"usage":2.16213,"raw":128,"avg":0.0496399607926,"vc":63,"abilities":[{"name":"Cursed Body","usage":65.291},{"name":"Clear Body","usage":33.6},{"name":"Infiltrator","usage":1.109}],"moves":[{"name":"Phantom Force","usage":99.632},{"name":"Outrage","usage":99.632},{"name":"Dragon Dance","usage":72.135},{"name":"Breaking Swipe","usage":50.942},{"name":"U-turn","usage":27.865},{"name":"Steel Wing","usage":27.498},{"name":"Psychic Fangs","usage":14.716},{"name":"Other","usage":7.579}],"items":[{"name":"Choice Scarf","usage":51.31},{"name":"Choice Band","usage":27.498},{"name":"Lum Berry","usage":14.348},{"name":"Flame Orb","usage":5.735},{"name":"Other","usage":1.109}],"spreads":[{"nature":"Adamant","evs":{"hp":0,"atk":252,"def":0,"spa":0,"spd":4,"spe":252},"usage":72.135},{"nature":"Jolly","evs":{"hp":0,"atk":252,"def":0,"spa":0,"spd":4,"spe":252},"usage":27.498},{"nature":"Other","evs":{"hp":null,"atk":null,"def":null,"spa":null,"spd":null,"spe":null},"usage":0.368}],"teammates":[{"name":"Ferroseed","usage":43.97},{"name":"Corsola-Galar","usage":28.606},{"name":"Brionne","usage":27.498},{"name":"Combusken","usage":27.498},{"name":"Hattrem","usage":27.498},{"name":"Thwackey","usage":15.457},{"name":"Scraggy","usage":14.348},{"name":"Klang","usage":14.348},{"name":"Dusclops","usage":14.348},{"name":"Golbat","usage":2.492},{"name":"Boldore","usage":2.124}],"counters":[],"lead":{"usage":0.05275,"raw":11,"rawp":0.973}},"carkol":{"usage":1.98749,"raw":59,"avg":0.0585424941447,"vc":61,"abilities":[{"name":"Flame Body","usage":100},{"name":"Flash Fire","usage":0},{"name":"Steam Engine","usage":0}],"moves":[{"name":"Will-O-Wisp","usage":100},{"name":"Heat Crash","usage":100},{"name":"Stealth Rock","usage":100},{"name":"Rapid Spin","usage":100},{"name":"Other","usage":0}],"items":[{"name":"Eviolite","usage":100},{"name":"Other","usage":0}],"spreads":[{"nature":"Careful","evs":{"hp":248,"atk":0,"def":8,"spa":0,"spd":252,"spe":0},"usage":100},{"nature":"Other","evs":{"hp":null,"atk":null,"def":null,"spa":null,"spd":null,"spe":null},"usage":0}],"teammates":[{"name":"Morgrem","usage":76.212},{"name":"Electabuzz","usage":76.212},{"name":"Dragonair","usage":76.212},{"name":"Nuzleaf","usage":76.212},{"name":"Roselia","usage":76.212}],"counters":[],"lead":{"usage":1.17506,"raw":16,"rawp":1.416}},"nuzleaf":{"usage":1.98749,"raw":29,"avg":0.0804959294489,"vc":60,"abilities":[{"name":"Pickpocket","usage":100},{"name":"Chlorophyll","usage":0}],"moves":[{"name":"Rock Slide","usage":100},{"name":"Leaf Blade","usage":100},{"name":"Swords Dance","usage":100},{"name":"Sucker Punch","usage":100},{"name":"Other","usage":0}],"items":[{"name":"Eviolite","usage":100},{"name":"Other","usage":0}],"spreads":[{"nature":"Adamant","evs":{"hp":248,"atk":252,"def":0,"spa":0,"spd":8,"spe":0},"usage":100},{"nature":"Other","evs":{"hp":null,"atk":null,"def":null,"spa":null,"spd":null,"spe":null},"usage":0}],"teammates":[{"name":"Morgrem","usage":76.212},{"name":"Dragonair","usage":76.212},{"name":"Electabuzz","usage":76.212},{"name":"Carkol","usage":76.212},{"name":"Roselia","usage":76.212}],"counters":[],"lead":{"usage":0,"raw":2,"rawp":0.177}},"sliggoo":{"usage":1.40083,"raw":46,"avg":0.0798268190293,"vc":80,"abilities":[{"name":"Sap Sipper","usage":97.353},{"name":"Gooey","usage":2.647},{"name":"Hydration","usage":0}],"moves":[{"name":"Ice Beam","usage":98.751},{"name":"Rest","usage":97.353},{"name":"Sleep Talk","usage":97.353},{"name":"Dragon Breath","usage":96.104},{"name":"Other","usage":10.439}],"items":[{"name":"Eviolite","usage":97.353},{"name":"Other","usage":2.647}],"spreads":[{"nature":"Modest","evs":{"hp":252,"atk":0,"def":0,"spa":252,"spd":4,"spe":0},"usage":96.104},{"nature":"Other","evs":{"hp":null,"atk":null,"def":null,"spa":null,"spd":null,"spe":null},"usage":3.896}],"teammates":[{"name":"Piloswine","usage":98.751},{"name":"Swirlix","usage":96.104},{"name":"Abra","usage":96.104},{"name":"Woobat","usage":96.104},{"name":"Charjabug","usage":96.104},{"name":"Charjabug","usage":96.104}],"counters":[],"lead":{"usage":0,"raw":1,"rawp":0.088}},"cutiefly":{"usage":1.39117,"raw":60,"avg":0.0412236260392,"vc":68,"abilities":[{"name":"Shield Dust","usage":56.841},{"name":"Sweet Veil","usage":43.159},{"name":"Honey Gather","usage":0}],"moves":[{"name":"Sticky Web","usage":100},{"name":"Sunny Day","usage":56.841},{"name":"Moonblast","usage":56.841},{"name":"Bug Buzz","usage":56.841},{"name":"U-turn","usage":43.159},{"name":"Tailwind","usage":43.159},{"name":"Trick","usage":43.159},{"name":"Other","usage":0}],"items":[{"name":"Heat Rock","usage":56.841},{"name":"Focus Sash","usage":43.159},{"name":"Other","usage":0}],"spreads":[{"nature":"Timid","evs":{"hp":0,"atk":0,"def":0,"spa":252,"spd":4,"spe":252},"usage":56.841},{"nature":"Jolly","evs":{"hp":248,"atk":0,"def":0,"spa":0,"spd":8,"spe":252},"usage":43.159},{"nature":"Other","evs":{"hp":null,"atk":null,"def":null,"spa":null,"spd":null,"spe":null},"usage":0}],"teammates":[{"name":"Wartortle","usage":100},{"name":"Fraxure","usage":56.841},{"name":"Metang","usage":56.841},{"name":"Ivysaur","usage":56.841},{"name":"Charmeleon","usage":56.841},{"name":"Hattrem","usage":43.159},{"name":"Electabuzz","usage":43.159},{"name":"Dusclops","usage":43.159},{"name":"Lombre","usage":23.899},{"name":"Lombre","usage":23.899}],"counters":[],"lead":{"usage":1.39117,"raw":34,"rawp":3.009}},"zweilous":{"usage":1.36656,"raw":42,"avg":0.112484291742,"vc":81,"abilities":[{"name":"Hustle","usage":100}],"moves":[{"name":"Crunch","usage":100},{"name":"Head Smash","usage":100},{"name":"Outrage","usage":100},{"name":"Superpower","usage":96.127},{"name":"Other","usage":3.873}],"items":[{"name":"Choice Band","usage":100},{"name":"Other","usage":0}],"spreads":[{"nature":"Jolly","evs":{"hp":0,"atk":252,"def":0,"spa":0,"spd":4,"spe":252},"usage":96.127},{"nature":"Other","evs":{"hp":null,"atk":null,"def":null,"spa":null,"spd":null,"spe":null},"usage":3.873}],"teammates":[{"name":"Gurdurr","usage":96.127},{"name":"Corsola-Galar","usage":96.127},{"name":"Magmar","usage":96.127},{"name":"Electabuzz","usage":96.127},{"name":"Klang","usage":96.127},{"name":"Klang","usage":96.127}],"counters":[],"lead":{"usage":0,"raw":1,"rawp":0.088}},"woobat":{"usage":1.34625,"raw":14,"avg":0.124664685374,"vc":80,"abilities":[{"name":"Simple","usage":100}],"moves":[{"name":"Giga Drain","usage":100},{"name":"Psychic","usage":100},{"name":"Air Slash","usage":100},{"name":"Nasty Plot","usage":100},{"name":"Other","usage":0}],"items":[{"name":"Eviolite","usage":100},{"name":"Other","usage":0}],"spreads":[{"nature":"Timid","evs":{"hp":4,"atk":0,"def":0,"spa":252,"spd":0,"spe":252},"usage":100},{"nature":"Other","evs":{"hp":null,"atk":null,"def":null,"spa":null,"spd":null,"spe":null},"usage":0}],"teammates":[{"name":"Swirlix","usage":100},{"name":"Abra","usage":100},{"name":"Charjabug","usage":100},{"name":"Sliggoo","usage":100},{"name":"Piloswine","usage":100},{"name":"Piloswine","usage":100}],"counters":[],"lead":{"usage":0,"raw":2,"rawp":0.177}},"swirlix":{"usage":1.34625,"raw":36,"avg":0.332439160998,"vc":80,"abilities":[{"name":"Unburden","usage":100}],"moves":[{"name":"Dazzling Gleam","usage":100},{"name":"Sticky Web","usage":100},{"name":"Yawn","usage":100},{"name":"Wish","usage":100},{"name":"Other","usage":0}],"items":[{"name":"Eviolite","usage":100},{"name":"Other","usage":0}],"spreads":[{"nature":"Bold","evs":{"hp":252,"atk":0,"def":252,"spa":4,"spd":0,"spe":0},"usage":100},{"nature":"Other","evs":{"hp":null,"atk":null,"def":null,"spa":null,"spd":null,"spe":null},"usage":0}],"teammates":[{"name":"Piloswine","usage":100},{"name":"Abra","usage":100},{"name":"Charjabug","usage":100},{"name":"Woobat","usage":100},{"name":"Sliggoo","usage":100},{"name":"Sliggoo","usage":100}],"counters":[],"lead":{"usage":0,"raw":4,"rawp":0.354}},"abra":{"usage":1.34625,"raw":41,"avg":0.0831097902496,"vc":80,"abilities":[{"name":"Magic Guard","usage":100},{"name":"Synchronize","usage":0},{"name":"Inner Focus","usage":0}],"moves":[{"name":"Shadow Ball","usage":100},{"name":"Psychic","usage":100},{"name":"Energy Ball","usage":100},{"name":"Dazzling Gleam","usage":100},{"name":"Other","usage":0}],"items":[{"name":"Choice Specs","usage":100},{"name":"Other","usage":0}],"spreads":[{"nature":"Modest","evs":{"hp":0,"atk":0,"def":4,"spa":252,"spd":0,"spe":252},"usage":100},{"nature":"Other","evs":{"hp":null,"atk":null,"def":null,"spa":null,"spd":null,"spe":null},"usage":0}],"teammates":[{"name":"Swirlix","usage":100},{"name":"Piloswine","usage":100},{"name":"Charjabug","usage":100},{"name":"Woobat","usage":100},{"name":"Sliggoo","usage":100},{"name":"Sliggoo","usage":100}],"counters":[],"lead":{"usage":0,"raw":5,"rawp":0.442}},"lairon":{"usage":1.33442,"raw":46,"avg":0.0411897374479,"vc":78,"abilities":[{"name":"Rock Head","usage":100},{"name":"Heavy Metal","usage":0},{"name":"Sturdy","usage":0}],"moves":[{"name":"Heavy Slam","usage":100},{"name":"Head Smash","usage":100},{"name":"Earthquake","usage":100},{"name":"Stealth Rock","usage":100},{"name":"Other","usage":0}],"items":[{"name":"Eviolite","usage":100},{"name":"Other","usage":0}],"spreads":[{"nature":"Adamant","evs":{"hp":0,"atk":252,"def":4,"spa":0,"spd":252,"spe":0},"usage":100},{"nature":"Other","evs":{"hp":null,"atk":null,"def":null,"spa":null,"spd":null,"spe":null},"usage":0}],"teammates":[{"name":"Lickitung","usage":100},{"name":"Pupitar","usage":100},{"name":"Corsola-Galar","usage":100},{"name":"Golbat","usage":100},{"name":"Magmar","usage":100},{"name":"Magmar","usage":100}],"counters":[],"lead":{"usage":0,"raw":13,"rawp":1.15}},"seadra":{"usage":1.33217,"raw":46,"avg":0.0429079653628,"vc":70,"abilities":[{"name":"Sniper","usage":100},{"name":"Poison Point","usage":0}],"moves":[{"name":"Surf","usage":100},{"name":"Ice Beam","usage":100},{"name":"Dragon Pulse","usage":50.337},{"name":"Flash Cannon","usage":50.337},{"name":"Agility","usage":49.663},{"name":"Focus Energy","usage":49.663},{"name":"Other","usage":0}],"items":[{"name":"Scope Lens","usage":50.337},{"name":"Eviolite","usage":49.663},{"name":"Other","usage":0}],"spreads":[{"nature":"Timid","evs":{"hp":0,"atk":0,"def":0,"spa":252,"spd":4,"spe":252},"usage":50.337},{"nature":"Naive","evs":{"hp":0,"atk":0,"def":0,"spa":252,"spd":4,"spe":252},"usage":49.663},{"nature":"Other","evs":{"hp":null,"atk":null,"def":null,"spa":null,"spd":null,"spe":null},"usage":0}],"teammates":[{"name":"Brionne","usage":50.337},{"name":"Tangela","usage":50.337},{"name":"Dragonair","usage":50.337},{"name":"Klang","usage":50.337},{"name":"Dartrix","usage":50.337},{"name":"Linoone-Galar","usage":49.663},{"name":"Electabuzz","usage":49.663},{"name":"Combusken","usage":49.663},{"name":"Corsola-Galar","usage":49.663},{"name":"Golbat","usage":49.663},{"name":"Golbat","usage":49.663}],"counters":[],"lead":{"usage":0.66159,"raw":4,"rawp":0.354}},"charmeleon":{"usage":1.28742,"raw":20,"avg":0.0733641713841,"vc":68,"abilities":[{"name":"Solar Power","usage":61.421},{"name":"Blaze","usage":38.579}],"moves":[{"name":"Ancient Power","usage":100},{"name":"Dragon Pulse","usage":100},{"name":"Weather Ball","usage":61.421},{"name":"Fire Blast","usage":61.421},{"name":"Flame Charge","usage":38.579},{"name":"Flamethrower","usage":38.579},{"name":"Other","usage":0}],"items":[{"name":"Choice Specs","usage":61.421},{"name":"Eviolite","usage":38.579},{"name":"Other","usage":0}],"spreads":[{"nature":"Modest","evs":{"hp":0,"atk":0,"def":0,"spa":252,"spd":4,"spe":252},"usage":61.421},{"nature":"Timid","evs":{"hp":0,"atk":0,"def":0,"spa":252,"spd":4,"spe":252},"usage":38.579},{"nature":"Other","evs":{"hp":null,"atk":null,"def":null,"spa":null,"spd":null,"spe":null},"usage":0}],"teammates":[{"name":"Wartortle","usage":100},{"name":"Ivysaur","usage":100},{"name":"Fraxure","usage":61.421},{"name":"Metang","usage":61.421},{"name":"Cutiefly","usage":61.421},{"name":"Electabuzz","usage":38.579},{"name":"Dragonair","usage":38.579},{"name":"Machoke","usage":38.579},{"name":"Machoke","usage":38.579}],"counters":[],"lead":{"usage":0,"raw":1,"rawp":0.088}},"lombre":{"usage":1.22088,"raw":28,"avg":0.239639855177,"vc":70,"abilities":[{"name":"Swift Swim","usage":100},{"name":"Own Tempo","usage":0},{"name":"Rain Dish","usage":0}],"moves":[{"name":"Rain Dance","usage":100},{"name":"Hydro Pump","usage":82.87},{"name":"Energy Ball","usage":82.87},{"name":"Whirlpool","usage":82.87},{"name":"Surf","usage":17.13},{"name":"Giga Drain","usage":17.13},{"name":"Other","usage":17.13}],"items":[{"name":"Eviolite","usage":82.87},{"name":"Damp Rock","usage":17.13},{"name":"Other","usage":0}],"spreads":[{"nature":"Modest","evs":{"hp":0,"atk":0,"def":0,"spa":252,"spd":4,"spe":252},"usage":82.87},{"nature":"Bold","evs":{"hp":0,"atk":0,"def":252,"spa":0,"spd":4,"spe":252},"usage":17.13},{"nature":"Other","evs":{"hp":null,"atk":null,"def":null,"spa":null,"spd":null,"spe":null},"usage":0}],"teammates":[{"name":"Electabuzz","usage":62.903},{"name":"Wartortle","usage":62.903},{"name":"Dwebble","usage":45.773},{"name":"Linoone-Galar","usage":45.773},{"name":"Brionne","usage":45.773},{"name":"Dusclops","usage":17.13},{"name":"Hattrem","usage":17.13},{"name":"Cutiefly","usage":17.13}],"counters":[],"lead":{"usage":0,"raw":1,"rawp":0.088}},"trubbish":{"usage":1.194,"raw":5,"avg":0.442262715094,"vc":77,"abilities":[{"name":"Sticky Hold","usage":100},{"name":"Aftermath","usage":0}],"moves":[{"name":"Spikes","usage":100},{"name":"Toxic Spikes","usage":100},{"name":"Acid Spray","usage":100},{"name":"Pain Split","usage":100},{"name":"Other","usage":0}],"items":[{"name":"Eviolite","usage":100}],"spreads":[{"nature":"Bold","evs":{"hp":252,"atk":0,"def":128,"spa":0,"spd":128,"spe":0},"usage":100},{"nature":"Other","evs":{"hp":null,"atk":null,"def":null,"spa":null,"spd":null,"spe":null},"usage":0}],"teammates":[{"name":"Tangela","usage":100},{"name":"Piloswine","usage":100},{"name":"Raboot","usage":100},{"name":"Electabuzz","usage":100},{"name":"Vullaby","usage":100},{"name":"Vullaby","usage":100}],"counters":[],"lead":{"usage":0,"raw":1,"rawp":0.088}},"fletchinder":{"usage":1.10398,"raw":179,"avg":0.0476316261662,"vc":69,"abilities":[{"name":"Gale Wings","usage":92.048},{"name":"Flame Body","usage":7.952}],"moves":[{"name":"U-turn","usage":100},{"name":"Defog","usage":92.048},{"name":"Thief","usage":92.048},{"name":"Acrobatics","usage":92.048},{"name":"Overheat","usage":7.952},{"name":"Other","usage":15.904}],"items":[{"name":"Nothing","usage":92.048},{"name":"Heavy-Duty Boots","usage":7.952},{"name":"Other","usage":0}],"spreads":[{"nature":"Jolly","evs":{"hp":0,"atk":252,"def":0,"spa":0,"spd":4,"spe":252},"usage":92.048},{"nature":"Naive","evs":{"hp":248,"atk":8,"def":0,"spa":0,"spd":0,"spe":252},"usage":7.952},{"nature":"Other","evs":{"hp":null,"atk":null,"def":null,"spa":null,"spd":null,"spe":null},"usage":0}],"teammates":[{"name":"Ferroseed","usage":10.731},{"name":"Electabuzz","usage":10.731},{"name":"Linoone-Galar","usage":7.952},{"name":"Brionne","usage":7.952},{"name":"Wartortle","usage":7.952},{"name":"Duosion","usage":2.78},{"name":"Krokorok","usage":2.78},{"name":"Corsola-Galar","usage":2.78}],"counters":[],"lead":{"usage":0,"raw":4,"rawp":0.354}},"gothorita":{"usage":0.88909,"raw":26,"avg":0.164662021848,"vc":63,"abilities":[{"name":"Competitive","usage":100},{"name":"Frisk","usage":0}],"moves":[{"name":"Psychic","usage":100},{"name":"Energy Ball","usage":100},{"name":"Nasty Plot","usage":95.829},{"name":"Shadow Ball","usage":95.829},{"name":"Other","usage":8.342}],"items":[{"name":"Eviolite","usage":95.829},{"name":"Other","usage":4.171}],"spreads":[{"nature":"Modest","evs":{"hp":0,"atk":0,"def":0,"spa":252,"spd":4,"spe":252},"usage":95.829},{"nature":"Other","evs":{"hp":null,"atk":null,"def":null,"spa":null,"spd":null,"spe":null},"usage":4.171}],"teammates":[{"name":"Gurdurr","usage":95.829},{"name":"Linoone-Galar","usage":95.829},{"name":"Lampent","usage":95.829},{"name":"Gabite","usage":95.829},{"name":"Togetic","usage":95.829},{"name":"Togetic","usage":95.829}],"counters":[],"lead":{"usage":0,"raw":1,"rawp":0.088}},"dwebble":{"usage":0.88841,"raw":16,"avg":0.397179476861,"vc":70,"abilities":[{"name":"Sturdy","usage":100}],"moves":[{"name":"Spikes","usage":100},{"name":"Stealth Rock","usage":100},{"name":"Knock Off","usage":100},{"name":"Shell Smash","usage":100},{"name":"Other","usage":0}],"items":[{"name":"Eviolite","usage":100},{"name":"Other","usage":0}],"spreads":[{"nature":"Adamant","evs":{"hp":0,"atk":252,"def":0,"spa":0,"spd":4,"spe":252},"usage":100},{"nature":"Other","evs":{"hp":null,"atk":null,"def":null,"spa":null,"spd":null,"spe":null},"usage":0}],"teammates":[{"name":"Lombre","usage":55.235},{"name":"Electabuzz","usage":55.235},{"name":"Wartortle","usage":55.235},{"name":"Linoone-Galar","usage":55.235},{"name":"Brionne","usage":55.235}],"counters":[],"lead":{"usage":0.88841,"raw":15,"rawp":1.327}},"omanyte":{"usage":0.79505,"raw":30,"avg":0.0625943141902,"vc":59,"abilities":[{"name":"Shell Armor","usage":100},{"name":"Weak Armor","usage":0}],"moves":[{"name":"Scald","usage":100},{"name":"Meteor Beam","usage":100},{"name":"Shell Smash","usage":100},{"name":"Ice Beam","usage":100},{"name":"Other","usage":0}],"items":[{"name":"White Herb","usage":83.861},{"name":"Eviolite","usage":16.139},{"name":"Other","usage":0}],"spreads":[{"nature":"Modest","evs":{"hp":0,"atk":0,"def":0,"spa":240,"spd":16,"spe":252},"usage":100},{"nature":"Other","evs":{"hp":null,"atk":null,"def":null,"spa":null,"spd":null,"spe":null},"usage":0}],"teammates":[{"name":"Piloswine","usage":72.38},{"name":"Fraxure","usage":72.38},{"name":"Electabuzz","usage":72.38},{"name":"Gurdurr","usage":72.38},{"name":"Dusclops","usage":72.38}],"counters":[],"lead":{"usage":0,"raw":6,"rawp":0.531}},"scraggy":{"usage":0.68263,"raw":16,"avg":0.045972461154,"vc":60,"abilities":[{"name":"Shed Skin","usage":100},{"name":"Intimidate","usage":0},{"name":"Moxie","usage":0}],"moves":[{"name":"Crunch","usage":100},{"name":"Dragon Dance","usage":100},{"name":"Rest","usage":100},{"name":"Drain Punch","usage":100},{"name":"Other","usage":0}],"items":[{"name":"Rocky Helmet","usage":100},{"name":"Other","usage":0}],"spreads":[{"nature":"Adamant","evs":{"hp":0,"atk":252,"def":0,"spa":0,"spd":4,"spe":252},"usage":100},{"nature":"Other","evs":{"hp":null,"atk":null,"def":null,"spa":null,"spd":null,"spe":null},"usage":0}],"teammates":[{"name":"Ferroseed","usage":100},{"name":"Klang","usage":100},{"name":"Thwackey","usage":100},{"name":"Dusclops","usage":100},{"name":"Drakloak","usage":100},{"name":"Drakloak","usage":100}],"counters":[],"lead":{"usage":0,"raw":0,"rawp":0}},"dartrix":{"usage":0.67057,"raw":36,"avg":0.0292216332436,"vc":59,"abilities":[{"name":"Long Reach","usage":100},{"name":"Overgrow","usage":0}],"moves":[{"name":"Brave Bird","usage":100},{"name":"Leaf Blade","usage":100},{"name":"Sucker Punch","usage":100},{"name":"Facade","usage":100},{"name":"Other","usage":0}],"items":[{"name":"Assault Vest","usage":100},{"name":"Other","usage":0}],"spreads":[{"nature":"Adamant","evs":{"hp":248,"atk":252,"def":0,"spa":0,"spd":8,"spe":0},"usage":100},{"nature":"Other","evs":{"hp":null,"atk":null,"def":null,"spa":null,"spd":null,"spe":null},"usage":0}],"teammates":[{"name":"Brionne","usage":100},{"name":"Tangela","usage":100},{"name":"Dragonair","usage":100},{"name":"Klang","usage":100},{"name":"Seadra","usage":100},{"name":"Seadra","usage":100}],"counters":[],"lead":{"usage":0,"raw":2,"rawp":0.177}},"machoke":{"usage":0.56545,"raw":73,"avg":0.0503254729498,"vc":70,"abilities":[{"name":"Guts","usage":82.232},{"name":"No Guard","usage":17.768}],"moves":[{"name":"Knock Off","usage":100},{"name":"Earthquake","usage":97.699},{"name":"Close Combat","usage":82.232},{"name":"Facade","usage":81.083},{"name":"Dynamic Punch","usage":17.768},{"name":"Bulk Up","usage":16.616},{"name":"Other","usage":4.602}],"items":[{"name":"Flame Orb","usage":82.232},{"name":"Eviolite","usage":16.616},{"name":"Other","usage":1.152}],"spreads":[{"nature":"Adamant","evs":{"hp":252,"atk":252,"def":0,"spa":0,"spd":4,"spe":0},"usage":82.235},{"nature":"Adamant","evs":{"hp":4,"atk":252,"def":252,"spa":0,"spd":0,"spe":0},"usage":16.616},{"nature":"Other","evs":{"hp":null,"atk":null,"def":null,"spa":null,"spd":null,"spe":null},"usage":1.149}],"teammates":[{"name":"Electabuzz","usage":16.616},{"name":"Ivysaur","usage":16.616},{"name":"Dragonair","usage":16.616},{"name":"Charmeleon","usage":16.616},{"name":"Wartortle","usage":16.616},{"name":"Gabite","usage":1.152},{"name":"Ponyta","usage":1.152},{"name":"Gurdurr","usage":1.152},{"name":"Wailmer","usage":1.152},{"name":"Palpitoad","usage":1.152},{"name":"Piloswine","usage":1.149}],"counters":[],"lead":{"usage":0,"raw":8,"rawp":0.708}},"palpitoad":{"usage":0.45641,"raw":39,"avg":0.0307378297459,"vc":61,"abilities":[{"name":"Water Absorb","usage":92.455},{"name":"Swift Swim","usage":7.545},{"name":"Hydration","usage":0}],"moves":[{"name":"Earth Power","usage":100},{"name":"Icy Wind","usage":92.455},{"name":"Scald","usage":92.455},{"name":"Stealth Rock","usage":92.455},{"name":"Surf","usage":7.545},{"name":"Other","usage":15.09}],"items":[{"name":"Leftovers","usage":92.455},{"name":"Rindo Berry","usage":7.545},{"name":"Other","usage":0}],"spreads":[{"nature":"Modest","evs":{"hp":156,"atk":0,"def":136,"spa":80,"spd":136,"spe":0},"usage":92.455},{"nature":"Modest","evs":{"hp":0,"atk":0,"def":0,"spa":252,"spd":4,"spe":252},"usage":7.545},{"nature":"Other","evs":{"hp":null,"atk":null,"def":null,"spa":null,"spd":null,"spe":null},"usage":0}],"teammates":[{"name":"Morgrem","usage":92.455},{"name":"Gastly","usage":92.455},{"name":"Metang","usage":92.455},{"name":"Raboot","usage":92.455},{"name":"Togetic","usage":92.455},{"name":"Gurdurr","usage":7.545},{"name":"Machoke","usage":7.545},{"name":"Machoke","usage":7.545}],"counters":[],"lead":{"usage":0,"raw":3,"rawp":0.265}},"gastly":{"usage":0.42198,"raw":61,"avg":0.0183885934549,"vc":63,"abilities":[{"name":"Levitate","usage":100}],"moves":[{"name":"Thunderbolt","usage":100},{"name":"Shadow Ball","usage":100},{"name":"Sludge Wave","usage":100},{"name":"Trick","usage":100},{"name":"Other","usage":0}],"items":[{"name":"Choice Scarf","usage":100},{"name":"Other","usage":0}],"spreads":[{"nature":"Modest","evs":{"hp":0,"atk":0,"def":0,"spa":252,"spd":0,"spe":252},"usage":100},{"nature":"Other","evs":{"hp":null,"atk":null,"def":null,"spa":null,"spd":null,"spe":null},"usage":0}],"teammates":[{"name":"Morgrem","usage":100},{"name":"Metang","usage":100},{"name":"Raboot","usage":100},{"name":"Togetic","usage":100},{"name":"Palpitoad","usage":100},{"name":"Palpitoad","usage":100}],"counters":[],"lead":{"usage":0.42198,"raw":4,"rawp":0.354}},"frillish":{"usage":0.33679,"raw":4,"avg":0.249500529451,"vc":58,"abilities":[{"name":"Water Absorb","usage":100}],"moves":[{"name":"Scald","usage":100},{"name":"Hex","usage":100},{"name":"Will-O-Wisp","usage":100},{"name":"Recover","usage":100},{"name":"Other","usage":0}],"items":[{"name":"Eviolite","usage":100},{"name":"Other","usage":0}],"spreads":[{"nature":"Bold","evs":{"hp":252,"atk":0,"def":252,"spa":0,"spd":4,"spe":0},"usage":100},{"nature":"Other","evs":{"hp":null,"atk":null,"def":null,"spa":null,"spd":null,"spe":null},"usage":0}],"teammates":[{"name":"Wartortle","usage":100},{"name":"Hattrem","usage":100},{"name":"Piloswine","usage":100},{"name":"Roselia","usage":100},{"name":"Clefairy","usage":100},{"name":"Clefairy","usage":100}],"counters":[],"lead":{"usage":0,"raw":0,"rawp":0}},"tentacool":{"usage":0.11696,"raw":11,"avg":0.0144406612342,"vc":53,"abilities":[{"name":"Clear Body","usage":100},{"name":"Liquid Ooze","usage":0}],"moves":[{"name":"Sludge Bomb","usage":100},{"name":"Surf","usage":100},{"name":"Toxic Spikes","usage":100},{"name":"Rapid Spin","usage":100},{"name":"Other","usage":0}],"items":[{"name":"Eviolite","usage":100},{"name":"Other","usage":0}],"spreads":[{"nature":"Hardy","evs":{"hp":196,"atk":0,"def":76,"spa":0,"spd":196,"spe":36},"usage":100},{"nature":"Other","evs":{"hp":null,"atk":null,"def":null,"spa":null,"spd":null,"spe":null},"usage":0}],"teammates":[{"name":"Morgrem","usage":100},{"name":"Duosion","usage":100},{"name":"Rufflet","usage":100},{"name":"Ferroseed","usage":100},{"name":"Marshtomp","usage":100},{"name":"Marshtomp","usage":100}],"counters":[],"lead":{"usage":0.11696,"raw":3,"rawp":0.265}},"boldore":{"usage":0.10105,"raw":70,"avg":0.00748652192285,"vc":59,"abilities":[{"name":"Sturdy","usage":100},{"name":"Sand Force","usage":0},{"name":"Weak Armor","usage":0}],"moves":[{"name":"Explosion","usage":100},{"name":"Protect","usage":100},{"name":"Autotomize","usage":100},{"name":"Stealth Rock","usage":100},{"name":"Other","usage":0}],"items":[{"name":"Red Card","usage":100},{"name":"Other","usage":0}],"spreads":[{"nature":"Impish","evs":{"hp":248,"atk":8,"def":252,"spa":0,"spd":0,"spe":0},"usage":100},{"nature":"Other","evs":{"hp":null,"atk":null,"def":null,"spa":null,"spd":null,"spe":null},"usage":0}],"teammates":[{"name":"Electabuzz","usage":37.032},{"name":"Raboot","usage":37.032},{"name":"Golbat","usage":37.032},{"name":"Ferroseed","usage":37.032},{"name":"Drakloak","usage":37.032}],"counters":[],"lead":{"usage":0.10105,"raw":19,"rawp":1.681}},"shelgon":{"usage":0.08206,"raw":6,"avg":0.0121587908441,"vc":65,"abilities":[{"name":"Rock Head","usage":100},{"name":"Overcoat","usage":0}],"moves":[{"name":"Crunch","usage":100},{"name":"Zen Headbutt","usage":100},{"name":"Double-Edge","usage":100},{"name":"Outrage","usage":100},{"name":"Other","usage":0}],"items":[{"name":"Assault Vest","usage":100},{"name":"Other","usage":0}],"spreads":[{"nature":"Adamant","evs":{"hp":252,"atk":252,"def":0,"spa":0,"spd":4,"spe":0},"usage":100},{"nature":"Other","evs":{"hp":null,"atk":null,"def":null,"spa":null,"spd":null,"spe":null},"usage":0}],"teammates":[{"name":"Metang","usage":100},{"name":"Hakamo-o","usage":100},{"name":"Raboot","usage":100},{"name":"Charjabug","usage":100},{"name":"Roselia","usage":100},{"name":"Roselia","usage":100}],"counters":[],"lead":{"usage":0,"raw":0,"rawp":0}},"hakamoo":{"usage":0.08206,"raw":61,"avg":0.00434280326717,"vc":55,"abilities":[{"name":"Bulletproof","usage":99.991},{"name":"Soundproof","usage":0.009},{"name":"Overcoat","usage":0}],"moves":[{"name":"Close Combat","usage":99.991},{"name":"X-Scissor","usage":99.991},{"name":"Outrage","usage":99.991},{"name":"Iron Head","usage":99.991},{"name":"Other","usage":0.035}],"items":[{"name":"Roseli Berry","usage":99.991},{"name":"Other","usage":0.009}],"spreads":[{"nature":"Adamant","evs":{"hp":252,"atk":252,"def":0,"spa":0,"spd":4,"spe":0},"usage":99.991},{"nature":"Other","evs":{"hp":null,"atk":null,"def":null,"spa":null,"spd":null,"spe":null},"usage":0.009}],"teammates":[{"name":"Shelgon","usage":99.991},{"name":"Charjabug","usage":99.991},{"name":"Metang","usage":99.991},{"name":"Raboot","usage":99.991},{"name":"Roselia","usage":99.991},{"name":"Roselia","usage":99.991}],"counters":[],"lead":{"usage":0,"raw":5,"rawp":0.442}},"wailmer":{"usage":0.03444,"raw":1,"avg":0.0255100384714,"vc":50,"abilities":[{"name":"Oblivious","usage":100}],"moves":[{"name":"Surf","usage":100},{"name":"Water Spout","usage":100},{"name":"Earthquake","usage":100},{"name":"Ice Beam","usage":100}],"items":[{"name":"Sitrus Berry","usage":100}],"spreads":[{"nature":"Mild","evs":{"hp":248,"atk":8,"def":0,"spa":252,"spd":0,"spe":0},"usage":100}],"teammates":[{"name":"Gabite","usage":100},{"name":"Machoke","usage":100},{"name":"Ponyta","usage":100},{"name":"Gurdurr","usage":100},{"name":"Palpitoad","usage":100}],"counters":[],"lead":{"usage":0.03444,"raw":1,"rawp":0.088}},"ponyta":{"usage":0.03444,"raw":2,"avg":0.0127550192357,"vc":50,"abilities":[{"name":"Flame Body","usage":100},{"name":"Flash Fire","usage":0}],"moves":[{"name":"Play Rough","usage":100},{"name":"High Horsepower","usage":100},{"name":"Flare Blitz","usage":100},{"name":"Wild Charge","usage":100},{"name":"Other","usage":0}],"items":[{"name":"Life Orb","usage":100},{"name":"Other","usage":0}],"spreads":[{"nature":"Jolly","evs":{"hp":0,"atk":252,"def":0,"spa":0,"spd":4,"spe":252},"usage":100}],"teammates":[{"name":"Gurdurr","usage":100},{"name":"Wailmer","usage":100},{"name":"Machoke","usage":100},{"name":"Palpitoad","usage":100},{"name":"Gabite","usage":100},{"name":"Gabite","usage":100}],"counters":[],"lead":{"usage":0,"raw":0,"rawp":0}},"kubfu":{"usage":0.02114,"raw":10,"avg":0.0156586797749,"vc":49,"abilities":[{"name":"Inner Focus","usage":100}],"moves":[{"name":"U-turn","usage":100},{"name":"Ice Punch","usage":100},{"name":"Close Combat","usage":100},{"name":"Iron Head","usage":100},{"name":"Other","usage":0}],"items":[{"name":"Assault Vest","usage":100},{"name":"Other","usage":0}],"spreads":[{"nature":"Adamant","evs":{"hp":252,"atk":252,"def":0,"spa":0,"spd":4,"spe":0},"usage":100},{"nature":"Other","evs":{"hp":null,"atk":null,"def":null,"spa":null,"spd":null,"spe":null},"usage":0}],"teammates":[{"name":"Wartortle","usage":100},{"name":"Ponyta-Galar","usage":100},{"name":"Combusken","usage":100},{"name":"Mudbray","usage":100},{"name":"Marshtomp","usage":100},{"name":"Marshtomp","usage":100}],"counters":[],"lead":{"usage":0,"raw":3,"rawp":0.265}},"ponytagalar":{"usage":0.02114,"raw":2,"avg":0.00782933988747,"vc":49,"abilities":[{"name":"Pastel Veil","usage":100},{"name":"Anticipation","usage":0}],"moves":[{"name":"Psychic","usage":100},{"name":"Play Rough","usage":100},{"name":"High Horsepower","usage":100},{"name":"Wild Charge","usage":100},{"name":"Other","usage":0}],"items":[{"name":"Assault Vest","usage":100},{"name":"Other","usage":0}],"spreads":[{"nature":"Hasty","evs":{"hp":0,"atk":252,"def":0,"spa":4,"spd":0,"spe":252},"usage":100},{"nature":"Other","evs":{"hp":null,"atk":null,"def":null,"spa":null,"spd":null,"spe":null},"usage":0}],"teammates":[{"name":"Marshtomp","usage":100},{"name":"Wartortle","usage":100},{"name":"Kubfu","usage":100},{"name":"Combusken","usage":100},{"name":"Mudbray","usage":100},{"name":"Mudbray","usage":100}],"counters":[],"lead":{"usage":0,"raw":0,"rawp":0}},"mudbray":{"usage":0.02114,"raw":1,"avg":0.0156586797749,"vc":49,"abilities":[{"name":"Stamina","usage":100}],"moves":[{"name":"Iron Head","usage":100},{"name":"Facade","usage":100},{"name":"Earthquake","usage":100},{"name":"Close Combat","usage":100}],"items":[{"name":"Assault Vest","usage":100}],"spreads":[{"nature":"Adamant","evs":{"hp":248,"atk":252,"def":0,"spa":0,"spd":8,"spe":0},"usage":100}],"teammates":[{"name":"Marshtomp","usage":100},{"name":"Ponyta-Galar","usage":100},{"name":"Kubfu","usage":100},{"name":"Wartortle","usage":100},{"name":"Combusken","usage":100}],"counters":[],"lead":{"usage":0,"raw":0,"rawp":0}},"onix":{"usage":0.01851,"raw":3,"avg":0.0137094549378,"vc":41,"abilities":[{"name":"Sturdy","usage":100},{"name":"Rock Head","usage":0}],"moves":[{"name":"Body Press","usage":100},{"name":"Toxic","usage":100},{"name":"Explosion","usage":100},{"name":"Stealth Rock","usage":100},{"name":"Other","usage":0}],"items":[{"name":"Custap Berry","usage":100},{"name":"Other","usage":0}],"spreads":[{"nature":"Careful","evs":{"hp":252,"atk":0,"def":4,"spa":0,"spd":252,"spe":0},"usage":100},{"nature":"Other","evs":{"hp":null,"atk":null,"def":null,"spa":null,"spd":null,"spe":null},"usage":0}],"teammates":[{"name":"Ferroseed","usage":100},{"name":"Corsola-Galar","usage":100},{"name":"Combusken","usage":100},{"name":"Gabite","usage":100},{"name":"Brionne","usage":100},{"name":"Brionne","usage":100}],"counters":[],"lead":{"usage":0.01851,"raw":1,"rawp":0.088}},"drizzile":{"usage":0.01835,"raw":24,"avg":0.0011325848914,"vc":63,"abilities":[{"name":"Torrent","usage":100},{"name":"Sniper","usage":0}],"moves":[{"name":"Bounce","usage":100},{"name":"Aqua Ring","usage":95.345},{"name":"Haze","usage":95.345},{"name":"Whirlpool","usage":95.345},{"name":"Other","usage":13.965}],"items":[{"name":"Leftovers","usage":95.345},{"name":"Other","usage":4.655}],"spreads":[{"nature":"Timid","evs":{"hp":0,"atk":0,"def":252,"spa":4,"spd":0,"spe":252},"usage":95.345},{"nature":"Other","evs":{"hp":null,"atk":null,"def":null,"spa":null,"spd":null,"spe":null},"usage":4.655}],"teammates":[{"name":"Amaura","usage":95.345},{"name":"Sliggoo","usage":95.345},{"name":"Poipole","usage":95.345},{"name":"Drakloak","usage":95.345},{"name":"Golbat","usage":95.345},{"name":"Golbat","usage":95.345}],"counters":[],"lead":{"usage":0,"raw":3,"rawp":0.265}},"amaura":{"usage":0.01749,"raw":5,"avg":0.0043194505268,"vc":47,"abilities":[{"name":"Snow Warning","usage":100}],"moves":[{"name":"Weather Ball","usage":100},{"name":"Blizzard","usage":100},{"name":"Stealth Rock","usage":100},{"name":"Aurora Veil","usage":100},{"name":"Other","usage":0}],"items":[{"name":"Light Clay","usage":100}],"spreads":[{"nature":"Timid","evs":{"hp":252,"atk":0,"def":0,"spa":0,"spd":4,"spe":252},"usage":100},{"nature":"Other","evs":{"hp":null,"atk":null,"def":null,"spa":null,"spd":null,"spe":null},"usage":0}],"teammates":[{"name":"Poipole","usage":100},{"name":"Sliggoo","usage":100},{"name":"Drakloak","usage":100},{"name":"Golbat","usage":100},{"name":"Drizzile","usage":100},{"name":"Drizzile","usage":100}],"counters":[],"lead":{"usage":0.01749,"raw":4,"rawp":0.354}},"poipole":{"usage":0.01749,"raw":37,"avg":0.000762255975318,"vc":60,"abilities":[{"name":"Beast Boost","usage":100}],"moves":[{"name":"Sludge Bomb","usage":100},{"name":"Dragon Pulse","usage":100},{"name":"Nasty Plot","usage":100},{"name":"Substitute","usage":100},{"name":"Other","usage":0}],"items":[{"name":"Eviolite","usage":100},{"name":"Other","usage":0}],"spreads":[{"nature":"Timid","evs":{"hp":0,"atk":0,"def":0,"spa":252,"spd":4,"spe":252},"usage":100},{"nature":"Other","evs":{"hp":null,"atk":null,"def":null,"spa":null,"spd":null,"spe":null},"usage":0}],"teammates":[{"name":"Drizzile","usage":100},{"name":"Amaura","usage":100},{"name":"Sliggoo","usage":100},{"name":"Golbat","usage":100},{"name":"Drakloak","usage":100},{"name":"Drakloak","usage":100}],"counters":[],"lead":{"usage":0,"raw":7,"rawp":0.619}}}