{"tangela":{"usage":63.02453,"raw":268,"avg":0.241352901352,"vc":89,"abilities":[{"name":"Regenerator","usage":100},{"name":"Chlorophyll","usage":0}],"moves":[{"name":"Knock Off","usage":99.69},{"name":"Sludge Bomb","usage":98.581},{"name":"Leaf Storm","usage":97.306},{"name":"Stun Spore","usage":96.996},{"name":"Other","usage":7.427}],"items":[{"name":"Eviolite","usage":100},{"name":"Other","usage":0}],"spreads":[{"nature":"Modest","evs":{"hp":80,"atk":0,"def":0,"spa":252,"spd":0,"spe":176},"usage":95.667},{"nature":"Other","evs":{"hp":null,"atk":null,"def":null,"spa":null,"spd":null,"spe":null},"usage":4.333}],"teammates":[{"name":"Linoone-Galar","usage":90.476},{"name":"Mareanie","usage":90.119},{"name":"Hattrem","usage":89.983},{"name":"Marshtomp","usage":88.937},{"name":"Magmar","usage":88.79},{"name":"Piloswine","usage":2.807},{"name":"Raboot","usage":2.671},{"name":"Gurdurr","usage":2.374},{"name":"Golbat","usage":1.969},{"name":"Duosion","usage":1.329},{"name":"Electabuzz","usage":1.105}],"counters":[],"lead":{"usage":7.68316,"raw":17,"rawp":1.586}},"linoonegalar":{"usage":62.4775,"raw":213,"avg":0.270998421312,"vc":89,"abilities":[{"name":"Quick Feet","usage":98.287},{"name":"Gluttony","usage":1.71},{"name":"Pickup","usage":0.004}],"moves":[{"name":"Parting Shot","usage":100},{"name":"Knock Off","usage":100},{"name":"Double-Edge","usage":96.37},{"name":"Protect","usage":96.366},{"name":"Other","usage":7.263}],"items":[{"name":"Eviolite","usage":97.873},{"name":"Other","usage":2.127}],"spreads":[{"nature":"Jolly","evs":{"hp":0,"atk":252,"def":0,"spa":0,"spd":4,"spe":252},"usage":99.61},{"nature":"Other","evs":{"hp":null,"atk":null,"def":null,"spa":null,"spd":null,"spe":null},"usage":0.39}],"teammates":[{"name":"Tangela","usage":91.137},{"name":"Hattrem","usage":90.491},{"name":"Magmar","usage":89.442},{"name":"Mareanie","usage":89.442},{"name":"Marshtomp","usage":89.438},{"name":"Raboot","usage":3.139},{"name":"Gabite","usage":1.713},{"name":"Cottonee","usage":1.71},{"name":"Poliwhirl","usage":1.71},{"name":"Gloom","usage":1.71},{"name":"Gurdurr","usage":1.053}],"counters":[],"lead":{"usage":32.25945,"raw":64,"rawp":5.97}},"mareanie":{"usage":61.10784,"raw":107,"avg":0.51953989785,"vc":89,"abilities":[{"name":"Regenerator","usage":100},{"name":"Merciless","usage":0}],"moves":[{"name":"Recover","usage":100},{"name":"Haze","usage":99.996},{"name":"Toxic Spikes","usage":99.876},{"name":"Knock Off","usage":98.615},{"name":"Other","usage":1.513}],"items":[{"name":"Eviolite","usage":100},{"name":"Other","usage":0}],"spreads":[{"nature":"Impish","evs":{"hp":252,"atk":0,"def":200,"spa":0,"spd":56,"spe":0},"usage":98.304},{"nature":"Other","evs":{"hp":null,"atk":null,"def":null,"spa":null,"spd":null,"spe":null},"usage":1.696}],"teammates":[{"name":"Tangela","usage":92.781},{"name":"Magmar","usage":91.511},{"name":"Linoone-Galar","usage":91.417},{"name":"Marshtomp","usage":91.414},{"name":"Hattrem","usage":91.413},{"name":"Piloswine","usage":1.462},{"name":"Gurdurr","usage":1.382},{"name":"Duosion","usage":1.37},{"name":"Golbat","usage":1.368}],"counters":[],"lead":{"usage":5.23108,"raw":9,"rawp":0.84}},"hattrem":{"usage":61.02974,"raw":160,"avg":0.492204903428,"vc":89,"abilities":[{"name":"Magic Bounce","usage":100}],"moves":[{"name":"Psychic","usage":99.983},{"name":"Giga Drain","usage":98.802},{"name":"Rest","usage":98.633},{"name":"Sleep Talk","usage":98.633},{"name":"Other","usage":3.95}],"items":[{"name":"Eviolite","usage":100},{"name":"Other","usage":0}],"spreads":[{"nature":"Bold","evs":{"hp":252,"atk":0,"def":252,"spa":0,"spd":0,"spe":4},"usage":98.633},{"nature":"Other","evs":{"hp":null,"atk":null,"def":null,"spa":null,"spd":null,"spe":null},"usage":1.367}],"teammates":[{"name":"Tangela","usage":92.772},{"name":"Linoone-Galar","usage":92.619},{"name":"Marshtomp","usage":91.694},{"name":"Mareanie","usage":91.542},{"name":"Magmar","usage":91.542},{"name":"Raboot","usage":1.23},{"name":"Gurdurr","usage":1.1},{"name":"Togetic","usage":1.078}],"counters":[],"lead":{"usage":3.24971,"raw":15,"rawp":1.399}},"magmar":{"usage":61.00644,"raw":264,"avg":0.349691819734,"vc":89,"abilities":[{"name":"Vital Spirit","usage":97.556},{"name":"Flame Body","usage":2.444}],"moves":[{"name":"Fire Blast","usage":99.824},{"name":"Psychic","usage":99.585},{"name":"Lava Plume","usage":99.313},{"name":"Scorching Sands","usage":98.185},{"name":"Other","usage":3.094}],"items":[{"name":"Choice Specs","usage":97.949},{"name":"Other","usage":2.051}],"spreads":[{"nature":"Modest","evs":{"hp":0,"atk":0,"def":0,"spa":252,"spd":4,"spe":252},"usage":99.315},{"nature":"Other","evs":{"hp":null,"atk":null,"def":null,"spa":null,"spd":null,"spe":null},"usage":0.685}],"teammates":[{"name":"Marshtomp","usage":90.815},{"name":"Mareanie","usage":90.639},{"name":"Linoone-Galar","usage":90.546},{"name":"Tangela","usage":90.542},{"name":"Hattrem","usage":90.542},{"name":"Golbat","usage":1.093},{"name":"Wartortle","usage":0.839},{"name":"Electabuzz","usage":0.839},{"name":"Ferroseed","usage":0.747},{"name":"Gurdurr","usage":0.747}],"counters":[],"lead":{"usage":1.16975,"raw":25,"rawp":2.332}},"marshtomp":{"usage":60.4156,"raw":145,"avg":0.535653424236,"vc":89,"abilities":[{"name":"Torrent","usage":100},{"name":"Damp","usage":0}],"moves":[{"name":"Earthquake","usage":100},{"name":"Stealth Rock","usage":100},{"name":"Rest","usage":99.568},{"name":"Sleep Talk","usage":99.568},{"name":"Other","usage":0.865}],"items":[{"name":"Eviolite","usage":100},{"name":"Other","usage":0}],"spreads":[{"nature":"Careful","evs":{"hp":248,"atk":0,"def":120,"spa":0,"spd":140,"spe":0},"usage":99.568},{"nature":"Other","evs":{"hp":null,"atk":null,"def":null,"spa":null,"spd":null,"spe":null},"usage":0.432}],"teammates":[{"name":"Magmar","usage":92.688},{"name":"Tangela","usage":92.563},{"name":"Hattrem","usage":92.563},{"name":"Mareanie","usage":92.41},{"name":"Linoone-Galar","usage":92.41}],"counters":[],"lead":{"usage":11.65366,"raw":35,"rawp":3.265}},"gurdurr":{"usage":33.26289,"raw":292,"avg":0.270068166653,"vc":91,"abilities":[{"name":"Guts","usage":99.793},{"name":"Iron Fist","usage":0.207},{"name":"Sheer Force","usage":0}],"moves":[{"name":"Knock Off","usage":99.966},{"name":"Drain Punch","usage":99.798},{"name":"Bulk Up","usage":98.092},{"name":"Mach Punch","usage":88.78},{"name":"Other","usage":13.364}],"items":[{"name":"Eviolite","usage":98.262},{"name":"Other","usage":1.738}],"spreads":[{"nature":"Adamant","evs":{"hp":252,"atk":252,"def":0,"spa":0,"spd":4,"spe":0},"usage":84.051},{"nature":"Adamant","evs":{"hp":252,"atk":252,"def":0,"spa":0,"spd":0,"spe":4},"usage":9.536},{"nature":"Adamant","evs":{"hp":248,"atk":252,"def":8,"spa":0,"spd":0,"spe":0},"usage":3.823},{"nature":"Other","evs":{"hp":null,"atk":null,"def":null,"spa":null,"spd":null,"spe":null},"usage":2.589}],"teammates":[{"name":"Thwackey","usage":74.043},{"name":"Golbat","usage":67.822},{"name":"Piloswine","usage":66.642},{"name":"Raboot","usage":66.186},{"name":"Ferroseed","usage":65.703},{"name":"Electabuzz","usage":10.72},{"name":"Clefairy","usage":9.574},{"name":"Corsola-Galar","usage":9.57},{"name":"Hakamo-o","usage":6.097},{"name":"Tangela","usage":3.824},{"name":"Klang","usage":3.44}],"counters":[],"lead":{"usage":3.28099,"raw":44,"rawp":4.104}},"thwackey":{"usage":32.17437,"raw":278,"avg":0.229626879679,"vc":91,"abilities":[{"name":"Grassy Surge","usage":100},{"name":"Overgrow","usage":0}],"moves":[{"name":"Grassy Glide","usage":100},{"name":"Swords Dance","usage":99.712},{"name":"Knock Off","usage":99.711},{"name":"Drain Punch","usage":87.664},{"name":"Other","usage":12.913}],"items":[{"name":"Eviolite","usage":99.704},{"name":"Other","usage":0.296}],"spreads":[{"nature":"Adamant","evs":{"hp":0,"atk":252,"def":0,"spa":0,"spd":4,"spe":252},"usage":97.428},{"nature":"Other","evs":{"hp":null,"atk":null,"def":null,"spa":null,"spd":null,"spe":null},"usage":2.572}],"teammates":[{"name":"Gurdurr","usage":76.937},{"name":"Golbat","usage":69.414},{"name":"Raboot","usage":69.3},{"name":"Piloswine","usage":67.185},{"name":"Ferroseed","usage":67.026},{"name":"Electabuzz","usage":10.08},{"name":"Clefairy","usage":9.913},{"name":"Corsola-Galar","usage":9.909},{"name":"Hakamo-o","usage":6.335},{"name":"Klang","usage":3.574},{"name":"Abra","usage":2.389}],"counters":[],"lead":{"usage":1.83892,"raw":26,"rawp":2.425}},"raboot":{"usage":31.34188,"raw":224,"avg":0.228903197536,"vc":91,"abilities":[{"name":"Libero","usage":100},{"name":"Blaze","usage":0}],"moves":[{"name":"Sucker Punch","usage":98.668},{"name":"High Jump Kick","usage":97.28},{"name":"Flare Blitz","usage":95.305},{"name":"Gunk Shot","usage":94.501},{"name":"Other","usage":14.246}],"items":[{"name":"Life Orb","usage":92.012},{"name":"Heavy-Duty Boots","usage":4.85},{"name":"Other","usage":3.138}],"spreads":[{"nature":"Jolly","evs":{"hp":0,"atk":252,"def":0,"spa":0,"spd":4,"spe":252},"usage":94.543},{"nature":"Adamant","evs":{"hp":188,"atk":252,"def":4,"spa":0,"spd":0,"spe":64},"usage":2.319},{"nature":"Other","evs":{"hp":null,"atk":null,"def":null,"spa":null,"spd":null,"spe":null},"usage":3.138}],"teammates":[{"name":"Golbat","usage":71.526},{"name":"Piloswine","usage":71.102},{"name":"Thwackey","usage":70.896},{"name":"Gurdurr","usage":70.358},{"name":"Ferroseed","usage":69.213},{"name":"Linoone-Galar","usage":5.335},{"name":"Tangela","usage":4.573},{"name":"Poliwhirl","usage":2.906},{"name":"Gabite","usage":2.906},{"name":"Cottonee","usage":2.906},{"name":"Gloom","usage":2.906}],"counters":[],"lead":{"usage":3.67371,"raw":22,"rawp":2.052}},"piloswine":{"usage":30.54648,"raw":284,"avg":0.219615333868,"vc":91,"abilities":[{"name":"Thick Fat","usage":100},{"name":"Oblivious","usage":0},{"name":"Snow Cloak","usage":0}],"moves":[{"name":"Icicle Crash","usage":100},{"name":"Ice Shard","usage":99.347},{"name":"Stealth Rock","usage":96.397},{"name":"Earthquake","usage":95.529},{"name":"Other","usage":8.727}],"items":[{"name":"Eviolite","usage":96.397},{"name":"Other","usage":3.603}],"spreads":[{"nature":"Adamant","evs":{"hp":252,"atk":252,"def":0,"spa":0,"spd":4,"spe":0},"usage":91.448},{"nature":"Adamant","evs":{"hp":0,"atk":252,"def":0,"spa":0,"spd":4,"spe":252},"usage":3.603},{"nature":"Other","evs":{"hp":null,"atk":null,"def":null,"spa":null,"spd":null,"spe":null},"usage":4.95}],"teammates":[{"name":"Golbat","usage":73.058},{"name":"Raboot","usage":72.67},{"name":"Gurdurr","usage":72.404},{"name":"Thwackey","usage":70.248},{"name":"Ferroseed","usage":70.08},{"name":"Electabuzz","usage":5.861},{"name":"Vullaby","usage":5.537},{"name":"Tangela","usage":4.911},{"name":"Clefairy","usage":4.256},{"name":"Roselia","usage":3.763},{"name":"Wartortle","usage":3.761}],"counters":[],"lead":{"usage":3.79893,"raw":65,"rawp":6.063}},"golbat":{"usage":30.10131,"raw":338,"avg":0.143032139665,"vc":91,"abilities":[{"name":"Infiltrator","usage":94.196},{"name":"Inner Focus","usage":5.804}],"moves":[{"name":"Sludge Bomb","usage":90.584},{"name":"Air Slash","usage":90.584},{"name":"Heat Wave","usage":90.584},{"name":"Nasty Plot","usage":90.584},{"name":"Roost","usage":9.125},{"name":"Defog","usage":8.656},{"name":"Other","usage":19.883}],"items":[{"name":"Eviolite","usage":98.779},{"name":"Other","usage":1.221}],"spreads":[{"nature":"Timid","evs":{"hp":0,"atk":0,"def":0,"spa":252,"spd":4,"spe":252},"usage":90.584},{"nature":"Impish","evs":{"hp":252,"atk":4,"def":252,"spa":0,"spd":0,"spe":0},"usage":2.703},{"nature":"Impish","evs":{"hp":248,"atk":0,"def":252,"spa":0,"spd":8,"spe":0},"usage":2.312},{"nature":"Other","evs":{"hp":null,"atk":null,"def":null,"spa":null,"spd":null,"spe":null},"usage":4.401}],"teammates":[{"name":"Gurdurr","usage":73.291},{"name":"Raboot","usage":72.712},{"name":"Piloswine","usage":72.667},{"name":"Thwackey","usage":72.189},{"name":"Ferroseed","usage":70.979},{"name":"Tangela","usage":3.427},{"name":"Abra","usage":2.485},{"name":"Fraxure","usage":2.357},{"name":"Cosmoem","usage":2.357},{"name":"Duosion","usage":2.312},{"name":"Mareanie","usage":2.312}],"counters":[],"lead":{"usage":3.28515,"raw":15,"rawp":1.399}},"ferroseed":{"usage":27.9341,"raw":243,"avg":0.235842307791,"vc":91,"abilities":[{"name":"Iron Barbs","usage":100}],"moves":[{"name":"Stealth Rock","usage":99.975},{"name":"Knock Off","usage":99.673},{"name":"Gyro Ball","usage":99.088},{"name":"Spikes","usage":96.709},{"name":"Other","usage":4.555}],"items":[{"name":"Eviolite","usage":100},{"name":"Other","usage":0}],"spreads":[{"nature":"Brave","evs":{"hp":252,"atk":252,"def":0,"spa":0,"spd":4,"spe":0},"usage":95.989},{"nature":"Other","evs":{"hp":null,"atk":null,"def":null,"spa":null,"spd":null,"spe":null},"usage":4.011}],"teammates":[{"name":"Gurdurr","usage":75.238},{"name":"Golbat","usage":75.214},{"name":"Raboot","usage":74.559},{"name":"Thwackey","usage":73.865},{"name":"Piloswine","usage":73.864},{"name":"Electabuzz","usage":2.18},{"name":"Magmar","usage":1.352},{"name":"Wartortle","usage":1.35},{"name":"Machoke","usage":0.695},{"name":"Clefairy","usage":0.695},{"name":"Dusclops","usage":0.695}],"counters":[],"lead":{"usage":16.38515,"raw":80,"rawp":7.463}},"electabuzz":{"usage":7.08408,"raw":335,"avg":0.0433091535254,"vc":86,"abilities":[{"name":"Static","usage":98.258},{"name":"Vital Spirit","usage":1.742}],"moves":[{"name":"Volt Switch","usage":99.999},{"name":"Thunderbolt","usage":99.305},{"name":"Focus Blast","usage":98.356},{"name":"Psychic","usage":67.27},{"name":"Seismic Toss","usage":17.915},{"name":"Other","usage":17.155}],"items":[{"name":"Choice Specs","usage":55.755},{"name":"Eviolite","usage":43.571},{"name":"Other","usage":0.674}],"spreads":[{"nature":"Timid","evs":{"hp":0,"atk":0,"def":0,"spa":252,"spd":4,"spe":252},"usage":95.89},{"nature":"Other","evs":{"hp":null,"atk":null,"def":null,"spa":null,"spd":null,"spe":null},"usage":4.11}],"teammates":[{"name":"Clefairy","usage":72.757},{"name":"Gurdurr","usage":57.936},{"name":"Thwackey","usage":52.427},{"name":"Corsola-Galar","usage":52.174},{"name":"Hakamo-o","usage":32.948},{"name":"Piloswine","usage":29.155},{"name":"Vullaby","usage":27.531},{"name":"Wartortle","usage":25.077},{"name":"Roselia","usage":18.705},{"name":"Klang","usage":18.59},{"name":"Raboot","usage":12.898}],"counters":[],"lead":{"usage":1.48371,"raw":62,"rawp":5.784}},"clefairy":{"usage":6.1178,"raw":194,"avg":0.0596237900086,"vc":84,"abilities":[{"name":"Magic Guard","usage":100},{"name":"Cute Charm","usage":0},{"name":"Friend Guard","usage":0}],"moves":[{"name":"Soft-Boiled","usage":99.992},{"name":"Moonblast","usage":99.966},{"name":"Stored Power","usage":69.901},{"name":"Calm Mind","usage":65.702},{"name":"Stealth Rock","usage":22.779},{"name":"Covet","usage":22.772},{"name":"Other","usage":18.888}],"items":[{"name":"Eviolite","usage":100},{"name":"Other","usage":0}],"spreads":[{"nature":"Bold","evs":{"hp":248,"atk":0,"def":252,"spa":4,"spd":0,"spe":4},"usage":65.513},{"nature":"Bold","evs":{"hp":252,"atk":0,"def":252,"spa":0,"spd":0,"spe":4},"usage":22.772},{"nature":"Calm","evs":{"hp":252,"atk":0,"def":128,"spa":24,"spd":104,"spe":0},"usage":4.172},{"nature":"Calm","evs":{"hp":252,"atk":0,"def":4,"spa":0,"spd":252,"spe":0},"usage":4.131},{"nature":"Other","evs":{"hp":null,"atk":null,"def":null,"spa":null,"spd":null,"spe":null},"usage":3.412}],"teammates":[{"name":"Electabuzz","usage":92.485},{"name":"Gurdurr","usage":65.771},{"name":"Corsola-Galar","usage":65.746},{"name":"Thwackey","usage":65.54},{"name":"Hakamo-o","usage":41.882},{"name":"Piloswine","usage":26.908},{"name":"Klang","usage":23.63},{"name":"Wartortle","usage":22.777},{"name":"Vullaby","usage":22.772},{"name":"Roselia","usage":22.772},{"name":"Raboot","usage":8.308}],"counters":[],"lead":{"usage":0.25286,"raw":22,"rawp":2.052}},"corsolagalar":{"usage":4.0739,"raw":209,"avg":0.0313280494064,"vc":84,"abilities":[{"name":"Cursed Body","usage":100},{"name":"Weak Armor","usage":0}],"moves":[{"name":"Night Shade","usage":100},{"name":"Strength Sap","usage":100},{"name":"Will-O-Wisp","usage":99.649},{"name":"Whirlpool","usage":98.435},{"name":"Other","usage":1.916}],"items":[{"name":"Eviolite","usage":100},{"name":"Other","usage":0}],"spreads":[{"nature":"Bold","evs":{"hp":252,"atk":0,"def":68,"spa":0,"spd":184,"spe":4},"usage":98.435},{"nature":"Other","evs":{"hp":null,"atk":null,"def":null,"spa":null,"spd":null,"spe":null},"usage":1.565}],"teammates":[{"name":"Electabuzz","usage":99.649},{"name":"Gurdurr","usage":98.786},{"name":"Clefairy","usage":98.786},{"name":"Thwackey","usage":98.435},{"name":"Hakamo-o","usage":62.93},{"name":"Klang","usage":35.505},{"name":"Klang","usage":35.505}],"counters":[],"lead":{"usage":0,"raw":31,"rawp":2.892}},"hakamoo":{"usage":2.56369,"raw":43,"avg":0.0998875424308,"vc":83,"abilities":[{"name":"Bulletproof","usage":100},{"name":"Overcoat","usage":0},{"name":"Soundproof","usage":0}],"moves":[{"name":"Swords Dance","usage":100},{"name":"Iron Tail","usage":100},{"name":"Earthquake","usage":100},{"name":"Drain Punch","usage":100},{"name":"Other","usage":0}],"items":[{"name":"Eviolite","usage":100},{"name":"Other","usage":0}],"spreads":[{"nature":"Adamant","evs":{"hp":0,"atk":252,"def":0,"spa":0,"spd":4,"spe":252},"usage":100},{"nature":"Other","evs":{"hp":null,"atk":null,"def":null,"spa":null,"spd":null,"spe":null},"usage":0}],"teammates":[{"name":"Gurdurr","usage":100},{"name":"Electabuzz","usage":100},{"name":"Thwackey","usage":100},{"name":"Clefairy","usage":100},{"name":"Corsola-Galar","usage":100},{"name":"Corsola-Galar","usage":100}],"counters":[],"lead":{"usage":2.56369,"raw":5,"rawp":0.466}},"klang":{"usage":2.54406,"raw":64,"avg":0.0773900908561,"vc":84,"abilities":[{"name":"Clear Body","usage":100},{"name":"Plus","usage":0}],"moves":[{"name":"Gear Grind","usage":100},{"name":"Shift Gear","usage":100},{"name":"Wild Charge","usage":96.061},{"name":"Substitute","usage":58.555},{"name":"Volt Switch","usage":41.445},{"name":"Other","usage":3.939}],"items":[{"name":"Eviolite","usage":100},{"name":"Other","usage":0}],"spreads":[{"nature":"Adamant","evs":{"hp":120,"atk":252,"def":0,"spa":0,"spd":0,"spe":136},"usage":58.555},{"nature":"Adamant","evs":{"hp":252,"atk":252,"def":0,"spa":0,"spd":4,"spe":0},"usage":41.445},{"nature":"Other","evs":{"hp":null,"atk":null,"def":null,"spa":null,"spd":null,"spe":null},"usage":0}],"teammates":[{"name":"Gurdurr","usage":54.617},{"name":"Corsola-Galar","usage":54.617},{"name":"Electabuzz","usage":54.617},{"name":"Thwackey","usage":54.617},{"name":"Clefairy","usage":54.617},{"name":"Lileep","usage":41.445},{"name":"Boldore","usage":41.445},{"name":"Herdier","usage":41.445},{"name":"Hippopotas","usage":41.445},{"name":"Krokorok","usage":32.131},{"name":"Abra","usage":9.314}],"counters":[],"lead":{"usage":0,"raw":1,"rawp":0.093}},"vullaby":{"usage":2.14309,"raw":75,"avg":0.066379809538,"vc":84,"abilities":[{"name":"Overcoat","usage":100},{"name":"Big Pecks","usage":0},{"name":"Weak Armor","usage":0}],"moves":[{"name":"Knock Off","usage":100},{"name":"Defog","usage":100},{"name":"Roost","usage":100},{"name":"U-turn","usage":65.328},{"name":"Whirlwind","usage":34.672},{"name":"Other","usage":0}],"items":[{"name":"Eviolite","usage":100},{"name":"Other","usage":0}],"spreads":[{"nature":"Impish","evs":{"hp":248,"atk":0,"def":240,"spa":0,"spd":0,"spe":20},"usage":64.593},{"nature":"Careful","evs":{"hp":252,"atk":0,"def":128,"spa":0,"spd":128,"spe":0},"usage":34.672},{"nature":"Other","evs":{"hp":null,"atk":null,"def":null,"spa":null,"spd":null,"spe":null},"usage":0.735}],"teammates":[{"name":"Piloswine","usage":99.309},{"name":"Electabuzz","usage":99.265},{"name":"Roselia","usage":64.637},{"name":"Wartortle","usage":64.593},{"name":"Clefairy","usage":64.593},{"name":"Raboot","usage":34.716},{"name":"Tangela","usage":34.672},{"name":"Trubbish","usage":34.672},{"name":"Trubbish","usage":34.672}],"counters":[],"lead":{"usage":0,"raw":13,"rawp":1.213}},"wartortle":{"usage":1.95198,"raw":210,"avg":0.0290291636432,"vc":86,"abilities":[{"name":"Torrent","usage":100},{"name":"Rain Dish","usage":0}],"moves":[{"name":"Rapid Spin","usage":100},{"name":"Toxic","usage":55.465},{"name":"Flip Turn","usage":55.465},{"name":"Seismic Toss","usage":52.526},{"name":"Ice Beam","usage":44.535},{"name":"Shell Smash","usage":44.535},{"name":"Surf","usage":40.578},{"name":"Other","usage":6.896}],"items":[{"name":"Eviolite","usage":100},{"name":"Other","usage":0}],"spreads":[{"nature":"Impish","evs":{"hp":252,"atk":0,"def":136,"spa":0,"spd":120,"spe":0},"usage":52.526},{"nature":"Modest","evs":{"hp":144,"atk":0,"def":0,"spa":252,"spd":0,"spe":112},"usage":40.578},{"nature":"Modest","evs":{"hp":0,"atk":0,"def":0,"spa":252,"spd":4,"spe":252},"usage":3.889},{"nature":"Other","evs":{"hp":null,"atk":null,"def":null,"spa":null,"spd":null,"spe":null},"usage":3.007}],"teammates":[{"name":"Electabuzz","usage":72.748},{"name":"Piloswine","usage":54.273},{"name":"Roselia","usage":54.261},{"name":"Clefairy","usage":51.981},{"name":"Vullaby","usage":51.969},{"name":"Magmar","usage":20.779},{"name":"Gurdurr","usage":18.487},{"name":"Ferroseed","usage":18.487},{"name":"Golbat","usage":18.487},{"name":"Mareanie","usage":2.303}],"counters":[],"lead":{"usage":0.00073,"raw":14,"rawp":1.306}},"roselia":{"usage":1.45636,"raw":60,"avg":0.051223576791,"vc":84,"abilities":[{"name":"Poison Point","usage":88.355},{"name":"Natural Cure","usage":11.645}],"moves":[{"name":"Sludge Bomb","usage":100},{"name":"Spikes","usage":99.941},{"name":"Synthesis","usage":99.938},{"name":"Stun Spore","usage":88.355},{"name":"Other","usage":11.766}],"items":[{"name":"Eviolite","usage":100},{"name":"Other","usage":0}],"spreads":[{"nature":"Bold","evs":{"hp":252,"atk":0,"def":220,"spa":0,"spd":0,"spe":36},"usage":88.355},{"nature":"Modest","evs":{"hp":0,"atk":0,"def":0,"spa":252,"spd":4,"spe":252},"usage":6.612},{"nature":"Calm","evs":{"hp":252,"atk":0,"def":4,"spa":0,"spd":252,"spe":0},"usage":4.971},{"nature":"Other","evs":{"hp":null,"atk":null,"def":null,"spa":null,"spd":null,"spe":null},"usage":0.062}],"teammates":[{"name":"Piloswine","usage":92.311},{"name":"Electabuzz","usage":92.251},{"name":"Wartortle","usage":92.251},{"name":"Vullaby","usage":88.415},{"name":"Clefairy","usage":88.355},{"name":"Magmar","usage":3.896},{"name":"Mareanie","usage":3.896}],"counters":[],"lead":{"usage":0.00094,"raw":5,"rawp":0.466}},"abra":{"usage":1.2135,"raw":35,"avg":0.0497701843775,"vc":78,"abilities":[{"name":"Magic Guard","usage":100},{"name":"Synchronize","usage":0}],"moves":[{"name":"Psychic","usage":100},{"name":"Shadow Ball","usage":100},{"name":"Counter","usage":71.815},{"name":"Energy Ball","usage":71.815},{"name":"Dazzling Gleam","usage":28.185},{"name":"Psyshock","usage":19.309},{"name":"Other","usage":8.875}],"items":[{"name":"Focus Sash","usage":71.815},{"name":"Life Orb","usage":19.309},{"name":"Choice Specs","usage":8.875},{"name":"Other","usage":0}],"spreads":[{"nature":"Modest","evs":{"hp":0,"atk":0,"def":0,"spa":252,"spd":4,"spe":252},"usage":71.815},{"nature":"Timid","evs":{"hp":0,"atk":0,"def":0,"spa":252,"spd":4,"spe":252},"usage":19.309},{"nature":"Timid","evs":{"hp":4,"atk":0,"def":0,"spa":252,"spd":0,"spe":252},"usage":8.875},{"nature":"Other","evs":{"hp":null,"atk":null,"def":null,"spa":null,"spd":null,"spe":null},"usage":0}],"teammates":[{"name":"Golbat","usage":75.689},{"name":"Thwackey","usage":75.689},{"name":"Fraxure","usage":71.815},{"name":"Cosmoem","usage":71.815},{"name":"Raboot","usage":71.815},{"name":"Lileep","usage":19.309},{"name":"Boldore","usage":19.309},{"name":"Klang","usage":19.309},{"name":"Hippopotas","usage":19.309},{"name":"Herdier","usage":19.309},{"name":"Sliggoo","usage":3.874}],"counters":[],"lead":{"usage":0,"raw":5,"rawp":0.466}},"poliwhirl":{"usage":1.15202,"raw":30,"avg":0.0612076474616,"vc":70,"abilities":[{"name":"Swift Swim","usage":100},{"name":"Water Absorb","usage":0}],"moves":[{"name":"Ice Punch","usage":100},{"name":"Waterfall","usage":100},{"name":"Brick Break","usage":100},{"name":"Swagger","usage":99.778},{"name":"Other","usage":0.222}],"items":[{"name":"Eviolite","usage":99.778},{"name":"Other","usage":0.222}],"spreads":[{"nature":"Jolly","evs":{"hp":96,"atk":252,"def":0,"spa":0,"spd":4,"spe":156},"usage":99.778},{"nature":"Other","evs":{"hp":null,"atk":null,"def":null,"spa":null,"spd":null,"spe":null},"usage":0.222}],"teammates":[{"name":"Cottonee","usage":99.778},{"name":"Linoone-Galar","usage":99.778},{"name":"Gloom","usage":99.778},{"name":"Gabite","usage":99.778},{"name":"Raboot","usage":99.778},{"name":"Raboot","usage":99.778}],"counters":[],"lead":{"usage":0,"raw":0,"rawp":0}},"gabite":{"usage":1.15189,"raw":82,"avg":0.0249334749961,"vc":77,"abilities":[{"name":"Rough Skin","usage":100},{"name":"Sand Veil","usage":0}],"moves":[{"name":"Earthquake","usage":100},{"name":"Sunny Day","usage":99.79},{"name":"Stealth Rock","usage":99.79},{"name":"Dragon Claw","usage":91.995},{"name":"Other","usage":8.425}],"items":[{"name":"Eviolite","usage":99.79},{"name":"Other","usage":0.21}],"spreads":[{"nature":"Jolly","evs":{"hp":0,"atk":252,"def":0,"spa":0,"spd":4,"spe":252},"usage":100},{"nature":"Other","evs":{"hp":null,"atk":null,"def":null,"spa":null,"spd":null,"spe":null},"usage":0}],"teammates":[{"name":"Linoone-Galar","usage":100},{"name":"Cottonee","usage":99.79},{"name":"Poliwhirl","usage":99.79},{"name":"Gloom","usage":99.79},{"name":"Raboot","usage":99.79},{"name":"Raboot","usage":99.79}],"counters":[],"lead":{"usage":0.07368,"raw":15,"rawp":1.399}},"gloom":{"usage":1.14988,"raw":52,"avg":0.0448019684165,"vc":70,"abilities":[{"name":"Chlorophyll","usage":99.964},{"name":"Stench","usage":0.036}],"moves":[{"name":"Sludge Bomb","usage":100},{"name":"Solar Beam","usage":99.964},{"name":"Moonblast","usage":99.964},{"name":"Giga Drain","usage":91.981},{"name":"Other","usage":8.091}],"items":[{"name":"Eviolite","usage":100},{"name":"Other","usage":0}],"spreads":[{"nature":"Modest","evs":{"hp":0,"atk":0,"def":0,"spa":252,"spd":4,"spe":252},"usage":99.964},{"nature":"Other","evs":{"hp":null,"atk":null,"def":null,"spa":null,"spd":null,"spe":null},"usage":0.036}],"teammates":[{"name":"Cottonee","usage":99.964},{"name":"Linoone-Galar","usage":99.964},{"name":"Poliwhirl","usage":99.964},{"name":"Gabite","usage":99.964},{"name":"Raboot","usage":99.964},{"name":"Raboot","usage":99.964}],"counters":[],"lead":{"usage":0,"raw":2,"rawp":0.187}},"cottonee":{"usage":1.14947,"raw":24,"avg":0.0746432706501,"vc":70,"abilities":[{"name":"Prankster","usage":100}],"moves":[{"name":"Knock Off","usage":100},{"name":"Sunny Day","usage":100},{"name":"Solar Beam","usage":91.978},{"name":"Tailwind","usage":61.311},{"name":"Defog","usage":38.689},{"name":"Other","usage":8.022}],"items":[{"name":"Eviolite","usage":100},{"name":"Other","usage":0}],"spreads":[{"nature":"Bold","evs":{"hp":252,"atk":0,"def":252,"spa":0,"spd":4,"spe":0},"usage":100},{"nature":"Other","evs":{"hp":null,"atk":null,"def":null,"spa":null,"spd":null,"spe":null},"usage":0}],"teammates":[{"name":"Gloom","usage":100},{"name":"Raboot","usage":100},{"name":"Poliwhirl","usage":100},{"name":"Gabite","usage":100},{"name":"Linoone-Galar","usage":100},{"name":"Linoone-Galar","usage":100}],"counters":[],"lead":{"usage":0.60778,"raw":10,"rawp":0.933}},"herdier":{"usage":1.11191,"raw":15,"avg":0.108306637073,"vc":72,"abilities":[{"name":"Sand Rush","usage":98.714},{"name":"Intimidate","usage":1.286},{"name":"Scrappy","usage":0}],"moves":[{"name":"Covet","usage":98.714},{"name":"Ice Fang","usage":98.714},{"name":"Take Down","usage":98.714},{"name":"Fire Fang","usage":98.714},{"name":"Other","usage":5.144}],"items":[{"name":"Normal Gem","usage":98.714},{"name":"Other","usage":1.286}],"spreads":[{"nature":"Adamant","evs":{"hp":0,"atk":252,"def":0,"spa":0,"spd":4,"spe":252},"usage":98.714},{"nature":"Other","evs":{"hp":null,"atk":null,"def":null,"spa":null,"spd":null,"spe":null},"usage":1.286}],"teammates":[{"name":"Lileep","usage":98.714},{"name":"Boldore","usage":98.714},{"name":"Klang","usage":98.714},{"name":"Hippopotas","usage":98.714},{"name":"Krokorok","usage":76.531},{"name":"Abra","usage":22.183},{"name":"Abra","usage":22.183}],"counters":[],"lead":{"usage":0.0143,"raw":5,"rawp":0.466}},"boldore":{"usage":1.0978,"raw":41,"avg":0.0377408634647,"vc":72,"abilities":[{"name":"Sand Force","usage":99.983},{"name":"Sturdy","usage":0.017},{"name":"Weak Armor","usage":0}],"moves":[{"name":"Body Press","usage":100},{"name":"Rock Slide","usage":99.983},{"name":"Earthquake","usage":99.983},{"name":"Stone Edge","usage":99.983},{"name":"Other","usage":0.052}],"items":[{"name":"Eviolite","usage":100},{"name":"Other","usage":0}],"spreads":[{"nature":"Adamant","evs":{"hp":248,"atk":252,"def":0,"spa":0,"spd":8,"spe":0},"usage":99.983},{"nature":"Other","evs":{"hp":null,"atk":null,"def":null,"spa":null,"spd":null,"spe":null},"usage":0.017}],"teammates":[{"name":"Lileep","usage":99.983},{"name":"Klang","usage":99.983},{"name":"Herdier","usage":99.983},{"name":"Hippopotas","usage":99.983},{"name":"Krokorok","usage":77.514},{"name":"Krokorok","usage":77.514}],"counters":[],"lead":{"usage":0.00019,"raw":10,"rawp":0.933}},"hippopotas":{"usage":1.09761,"raw":11,"avg":0.0916403895108,"vc":72,"abilities":[{"name":"Sand Stream","usage":100}],"moves":[{"name":"Slack Off","usage":100},{"name":"Stealth Rock","usage":100},{"name":"Toxic","usage":100},{"name":"Earthquake","usage":100},{"name":"Other","usage":0}],"items":[{"name":"Eviolite","usage":77.528},{"name":"Smooth Rock","usage":22.472},{"name":"Other","usage":0}],"spreads":[{"nature":"Impish","evs":{"hp":252,"atk":4,"def":252,"spa":0,"spd":0,"spe":0},"usage":100},{"nature":"Other","evs":{"hp":null,"atk":null,"def":null,"spa":null,"spd":null,"spe":null},"usage":0}],"teammates":[{"name":"Lileep","usage":100},{"name":"Boldore","usage":100},{"name":"Herdier","usage":100},{"name":"Klang","usage":100},{"name":"Krokorok","usage":77.528},{"name":"Krokorok","usage":77.528}],"counters":[],"lead":{"usage":0.89663,"raw":7,"rawp":0.653}},"lileep":{"usage":1.09761,"raw":4,"avg":0.160370681644,"vc":72,"abilities":[{"name":"Storm Drain","usage":100}],"moves":[{"name":"Sludge Bomb","usage":100},{"name":"Sandstorm","usage":100},{"name":"Recover","usage":100},{"name":"Giga Drain","usage":100}],"items":[{"name":"Eviolite","usage":100}],"spreads":[{"nature":"Calm","evs":{"hp":248,"atk":0,"def":0,"spa":8,"spd":252,"spe":0},"usage":100}],"teammates":[{"name":"Boldore","usage":100},{"name":"Herdier","usage":100},{"name":"Klang","usage":100},{"name":"Hippopotas","usage":100},{"name":"Krokorok","usage":77.528},{"name":"Krokorok","usage":77.528}],"counters":[],"lead":{"usage":0,"raw":0,"rawp":0}},"duosion":{"usage":0.95309,"raw":159,"avg":0.00723793095674,"vc":84,"abilities":[{"name":"Regenerator","usage":99.556},{"name":"Magic Guard","usage":0.444}],"moves":[{"name":"Recover","usage":99.951},{"name":"Shadow Ball","usage":99.582},{"name":"Future Sight","usage":94.35},{"name":"Protect","usage":94.347},{"name":"Other","usage":11.77}],"items":[{"name":"Eviolite","usage":99.954},{"name":"Other","usage":0.046}],"spreads":[{"nature":"Calm","evs":{"hp":252,"atk":0,"def":40,"spa":0,"spd":216,"spe":0},"usage":94.347},{"nature":"Modest","evs":{"hp":252,"atk":0,"def":0,"spa":252,"spd":4,"spe":0},"usage":5.453},{"nature":"Other","evs":{"hp":null,"atk":null,"def":null,"spa":null,"spd":null,"spe":null},"usage":0.2}],"teammates":[{"name":"Gurdurr","usage":94.552},{"name":"Piloswine","usage":94.478},{"name":"Mareanie","usage":94.476},{"name":"Tangela","usage":94.4},{"name":"Golbat","usage":94.348},{"name":"Electabuzz","usage":5.412},{"name":"Electabuzz","usage":5.412}],"counters":[],"lead":{"usage":0.0006,"raw":9,"rawp":0.84}},"cosmoem":{"usage":0.91736,"raw":14,"avg":0.0536137672862,"vc":78,"abilities":[{"name":"Sturdy","usage":100}],"moves":[{"name":"Nothing","usage":100},{"name":"Teleport","usage":100},{"name":"Splash","usage":100},{"name":"Cosmic Power","usage":100}],"items":[{"name":"Eviolite","usage":100},{"name":"Other","usage":0}],"spreads":[{"nature":"Sassy","evs":{"hp":252,"atk":0,"def":4,"spa":0,"spd":252,"spe":0},"usage":100},{"nature":"Other","evs":{"hp":null,"atk":null,"def":null,"spa":null,"spd":null,"spe":null},"usage":0}],"teammates":[{"name":"Abra","usage":100},{"name":"Fraxure","usage":100},{"name":"Raboot","usage":100},{"name":"Golbat","usage":100},{"name":"Thwackey","usage":100},{"name":"Thwackey","usage":100}],"counters":[],"lead":{"usage":0,"raw":3,"rawp":0.28}},"fraxure":{"usage":0.91736,"raw":126,"avg":0.0140837030098,"vc":78,"abilities":[{"name":"Mold Breaker","usage":100},{"name":"Rivalry","usage":0},{"name":"Unnerve","usage":0}],"moves":[{"name":"Poison Jab","usage":100},{"name":"First Impression","usage":92.849},{"name":"Outrage","usage":92.849},{"name":"Scale Shot","usage":92.849},{"name":"Aqua Tail","usage":7.151},{"name":"Other","usage":14.303}],"items":[{"name":"Choice Band","usage":92.849},{"name":"Leftovers","usage":7.151},{"name":"Other","usage":0}],"spreads":[{"nature":"Adamant","evs":{"hp":0,"atk":252,"def":4,"spa":0,"spd":0,"spe":252},"usage":92.849},{"nature":"Adamant","evs":{"hp":0,"atk":252,"def":0,"spa":0,"spd":4,"spe":252},"usage":7.151},{"nature":"Other","evs":{"hp":null,"atk":null,"def":null,"spa":null,"spd":null,"spe":null},"usage":0}],"teammates":[{"name":"Thwackey","usage":92.849},{"name":"Abra","usage":92.849},{"name":"Cosmoem","usage":92.849},{"name":"Raboot","usage":92.849},{"name":"Golbat","usage":92.849}],"counters":[],"lead":{"usage":0,"raw":8,"rawp":0.746}},"krokorok":{"usage":0.85095,"raw":54,"avg":0.0242735206445,"vc":72,"abilities":[{"name":"Moxie","usage":89.08},{"name":"Intimidate","usage":10.92},{"name":"Anger Point","usage":0}],"moves":[{"name":"Earthquake","usage":100},{"name":"Aqua Tail","usage":89.08},{"name":"Brick Break","usage":89.08},{"name":"Crunch","usage":89.08},{"name":"Taunt","usage":10.92},{"name":"Knock Off","usage":10.92},{"name":"Other","usage":10.92}],"items":[{"name":"Focus Sash","usage":89.08},{"name":"Eviolite","usage":10.92},{"name":"Other","usage":0}],"spreads":[{"nature":"Jolly","evs":{"hp":0,"atk":252,"def":0,"spa":0,"spd":4,"spe":252},"usage":89.08},{"nature":"Jolly","evs":{"hp":252,"atk":0,"def":152,"spa":0,"spd":0,"spe":104},"usage":10.92},{"nature":"Other","evs":{"hp":null,"atk":null,"def":null,"spa":null,"spd":null,"spe":null},"usage":0}],"teammates":[{"name":"Boldore","usage":89.08},{"name":"Herdier","usage":89.08},{"name":"Lileep","usage":89.08},{"name":"Klang","usage":89.08},{"name":"Hippopotas","usage":89.08}],"counters":[],"lead":{"usage":0.20098,"raw":12,"rawp":1.119}},"trubbish":{"usage":0.74823,"raw":13,"avg":0.145763739808,"vc":79,"abilities":[{"name":"Sticky Hold","usage":100},{"name":"Aftermath","usage":0}],"moves":[{"name":"Venoshock","usage":100},{"name":"Spikes","usage":100},{"name":"Toxic Spikes","usage":100},{"name":"Pain Split","usage":100},{"name":"Other","usage":0}],"items":[{"name":"Eviolite","usage":100},{"name":"Other","usage":0}],"spreads":[{"nature":"Bold","evs":{"hp":252,"atk":0,"def":128,"spa":0,"spd":128,"spe":0},"usage":100},{"nature":"Other","evs":{"hp":null,"atk":null,"def":null,"spa":null,"spd":null,"spe":null},"usage":0}],"teammates":[{"name":"Electabuzz","usage":100},{"name":"Raboot","usage":100},{"name":"Tangela","usage":100},{"name":"Piloswine","usage":100},{"name":"Vullaby","usage":100},{"name":"Vullaby","usage":100}],"counters":[],"lead":{"usage":0,"raw":7,"rawp":0.653}},"togetic":{"usage":0.70838,"raw":84,"avg":0.0147858277093,"vc":78,"abilities":[{"name":"Serene Grace","usage":100},{"name":"Super Luck","usage":0},{"name":"Hustle","usage":0}],"moves":[{"name":"Heal Bell","usage":99.942},{"name":"Wish","usage":99.942},{"name":"Defog","usage":99.942},{"name":"Encore","usage":99.942},{"name":"Other","usage":0.232}],"items":[{"name":"Eviolite","usage":100},{"name":"Other","usage":0}],"spreads":[{"nature":"Calm","evs":{"hp":248,"atk":0,"def":8,"spa":0,"spd":252,"spe":0},"usage":99.942},{"nature":"Other","evs":{"hp":null,"atk":null,"def":null,"spa":null,"spd":null,"spe":null},"usage":0.058}],"teammates":[{"name":"Gurdurr","usage":99.942},{"name":"Linoone-Galar","usage":99.942},{"name":"Tangela","usage":99.942},{"name":"Hattrem","usage":99.942},{"name":"Raboot","usage":99.942},{"name":"Raboot","usage":99.942}],"counters":[],"lead":{"usage":0,"raw":6,"rawp":0.56}},"dusclops":{"usage":0.50034,"raw":233,"avg":0.00295275863628,"vc":72,"abilities":[{"name":"Pressure","usage":80.983},{"name":"Frisk","usage":19.017}],"moves":[{"name":"Night Shade","usage":100},{"name":"Pain Split","usage":56.56},{"name":"Toxic","usage":45.309},{"name":"Rest","usage":42.838},{"name":"Sleep Talk","usage":42.838},{"name":"Substitute","usage":37.114},{"name":"Focus Punch","usage":35.245},{"name":"Will-O-Wisp","usage":19.446},{"name":"Haze","usage":19.017},{"name":"Other","usage":1.634}],"items":[{"name":"Eviolite","usage":100},{"name":"Other","usage":0}],"spreads":[{"nature":"Calm","evs":{"hp":252,"atk":0,"def":4,"spa":0,"spd":252,"spe":0},"usage":43.267},{"nature":"Adamant","evs":{"hp":248,"atk":252,"def":0,"spa":0,"spd":8,"spe":0},"usage":35.245},{"nature":"Bold","evs":{"hp":4,"atk":0,"def":252,"spa":0,"spd":252,"spe":0},"usage":20.886},{"nature":"Other","evs":{"hp":null,"atk":null,"def":null,"spa":null,"spd":null,"spe":null},"usage":0.603}],"teammates":[{"name":"Clefairy","usage":44.234},{"name":"Machoke","usage":44.23},{"name":"Raboot","usage":43.44},{"name":"Electabuzz","usage":43.267},{"name":"Ferroseed","usage":42.838},{"name":"Golbat","usage":38.663},{"name":"Tangela","usage":30.363},{"name":"Linoone-Galar","usage":30.363},{"name":"Porygon","usage":29.876},{"name":"Brionne","usage":19.612},{"name":"Thwackey","usage":9.332}],"counters":[],"lead":{"usage":0.00256,"raw":15,"rawp":1.399}},"machoke":{"usage":0.44549,"raw":86,"avg":0.00935788576129,"vc":72,"abilities":[{"name":"No Guard","usage":99.791},{"name":"Guts","usage":0.209},{"name":"Steadfast","usage":0}],"moves":[{"name":"Knock Off","usage":100},{"name":"Dynamic Punch","usage":99.791},{"name":"Rest","usage":59.449},{"name":"Sleep Talk","usage":56.964},{"name":"Bulk Up","usage":42.827},{"name":"Encore","usage":40.342},{"name":"Other","usage":0.628}],"items":[{"name":"Eviolite","usage":99.791},{"name":"Other","usage":0.209}],"spreads":[{"nature":"Impish","evs":{"hp":252,"atk":4,"def":252,"spa":0,"spd":0,"spe":0},"usage":56.964},{"nature":"Adamant","evs":{"hp":0,"atk":252,"def":4,"spa":0,"spd":0,"spe":252},"usage":40.342},{"nature":"Other","evs":{"hp":null,"atk":null,"def":null,"spa":null,"spd":null,"spe":null},"usage":2.694}],"teammates":[{"name":"Clefairy","usage":99.156},{"name":"Dusclops","usage":58.815},{"name":"Raboot","usage":57.173},{"name":"Electabuzz","usage":56.964},{"name":"Ferroseed","usage":56.964},{"name":"Golbat","usage":40.342},{"name":"Lairon","usage":40.342},{"name":"Magmar","usage":40.342},{"name":"Marshtomp","usage":40.342},{"name":"Marshtomp","usage":40.342}],"counters":[],"lead":{"usage":0.13031,"raw":12,"rawp":1.119}},"porygon":{"usage":0.27809,"raw":76,"avg":0.00290527737474,"vc":66,"abilities":[{"name":"Analytic","usage":67.028},{"name":"Download","usage":32.972},{"name":"Trace","usage":0}],"moves":[{"name":"Tri Attack","usage":100},{"name":"Ice Beam","usage":100},{"name":"Discharge","usage":67.028},{"name":"Recover","usage":67.028},{"name":"Thunderbolt","usage":32.972},{"name":"Psychic","usage":32.972},{"name":"Other","usage":0}],"items":[{"name":"Eviolite","usage":67.028},{"name":"Choice Specs","usage":32.972}],"spreads":[{"nature":"Modest","evs":{"hp":252,"atk":0,"def":0,"spa":252,"spd":4,"spe":0},"usage":67.028},{"nature":"Modest","evs":{"hp":0,"atk":0,"def":4,"spa":252,"spd":0,"spe":252},"usage":32.972},{"nature":"Other","evs":{"hp":null,"atk":null,"def":null,"spa":null,"spd":null,"spe":null},"usage":0}],"teammates":[{"name":"Tangela","usage":91.709},{"name":"Linoone-Galar","usage":58.737},{"name":"Golbat","usage":58.737},{"name":"Dusclops","usage":58.737},{"name":"Brionne","usage":37.601},{"name":"Hattrem","usage":32.972},{"name":"Raboot","usage":32.972},{"name":"Drakloak","usage":32.972},{"name":"Marshtomp","usage":32.972},{"name":"Palpitoad","usage":18.331},{"name":"Whirlipede","usage":2.153}],"counters":[],"lead":{"usage":0.0199,"raw":6,"rawp":0.56}},"lairon":{"usage":0.1809,"raw":51,"avg":0.00422897154259,"vc":76,"abilities":[{"name":"Rock Head","usage":100},{"name":"Heavy Metal","usage":0},{"name":"Sturdy","usage":0}],"moves":[{"name":"Head Smash","usage":100},{"name":"Heavy Slam","usage":100},{"name":"Superpower","usage":100},{"name":"Double-Edge","usage":99.98},{"name":"Other","usage":0.021}],"items":[{"name":"Choice Band","usage":100},{"name":"Other","usage":0}],"spreads":[{"nature":"Adamant","evs":{"hp":0,"atk":252,"def":0,"spa":0,"spd":4,"spe":252},"usage":100},{"nature":"Other","evs":{"hp":null,"atk":null,"def":null,"spa":null,"spd":null,"spe":null},"usage":0}],"teammates":[{"name":"Machoke","usage":99.98},{"name":"Golbat","usage":99.98},{"name":"Clefairy","usage":99.98},{"name":"Magmar","usage":99.98},{"name":"Marshtomp","usage":99.98},{"name":"Marshtomp","usage":99.98}],"counters":[],"lead":{"usage":0,"raw":5,"rawp":0.466}},"torracat":{"usage":0.1311,"raw":48,"avg":0.00391476799515,"vc":69,"abilities":[{"name":"Intimidate","usage":100},{"name":"Blaze","usage":0}],"moves":[{"name":"Flare Blitz","usage":99.973},{"name":"Will-O-Wisp","usage":76.181},{"name":"Swords Dance","usage":76.155},{"name":"Leech Life","usage":76.155},{"name":"U-turn","usage":23.845},{"name":"Parting Shot","usage":23.819},{"name":"Outrage","usage":23.819},{"name":"Other","usage":0.053}],"items":[{"name":"Heavy-Duty Boots","usage":99.973},{"name":"Other","usage":0.027}],"spreads":[{"nature":"Jolly","evs":{"hp":0,"atk":252,"def":0,"spa":0,"spd":4,"spe":252},"usage":99.973},{"nature":"Other","evs":{"hp":null,"atk":null,"def":null,"spa":null,"spd":null,"spe":null},"usage":0.027}],"teammates":[{"name":"Lampent","usage":39.29},{"name":"Combusken","usage":39.29},{"name":"Raboot","usage":39.29},{"name":"Magmar","usage":39.29},{"name":"Growlithe","usage":39.29},{"name":"Duosion","usage":23.845},{"name":"Linoone-Galar","usage":23.819},{"name":"Electabuzz","usage":23.819},{"name":"Ferroseed","usage":23.819},{"name":"Corsola-Galar","usage":23.819}],"counters":[],"lead":{"usage":0.03281,"raw":7,"rawp":0.653}},"brionne":{"usage":0.11692,"raw":78,"avg":0.00168215119166,"vc":61,"abilities":[{"name":"Liquid Voice","usage":100},{"name":"Torrent","usage":0}],"moves":[{"name":"Moonblast","usage":100},{"name":"Ice Beam","usage":100},{"name":"Echoed Voice","usage":100},{"name":"Hyper Voice","usage":100},{"name":"Other","usage":0}],"items":[{"name":"Choice Scarf","usage":100},{"name":"Other","usage":0}],"spreads":[{"nature":"Timid","evs":{"hp":0,"atk":0,"def":0,"spa":252,"spd":4,"spe":252},"usage":100},{"nature":"Other","evs":{"hp":null,"atk":null,"def":null,"spa":null,"spd":null,"spe":null},"usage":0}],"teammates":[{"name":"Linoone-Galar","usage":96.721},{"name":"Tangela","usage":96.721},{"name":"Dusclops","usage":96.721},{"name":"Golbat","usage":96.721},{"name":"Porygon","usage":94.32},{"name":"Porygon","usage":94.32}],"counters":[],"lead":{"usage":0,"raw":6,"rawp":0.56}},"drakloak":{"usage":0.09998,"raw":138,"avg":0.0025403456338,"vc":63,"abilities":[{"name":"Clear Body","usage":51.06},{"name":"Infiltrator","usage":48.94},{"name":"Cursed Body","usage":0}],"moves":[{"name":"Hex","usage":100},{"name":"Will-O-Wisp","usage":100},{"name":"Fire Blast","usage":100},{"name":"Thunder Wave","usage":51.06},{"name":"U-turn","usage":48.94},{"name":"Other","usage":0}],"items":[{"name":"Eviolite","usage":100},{"name":"Other","usage":0}],"spreads":[{"nature":"Timid","evs":{"hp":0,"atk":0,"def":0,"spa":252,"spd":4,"spe":252},"usage":100},{"nature":"Other","evs":{"hp":null,"atk":null,"def":null,"spa":null,"spd":null,"spe":null},"usage":0}],"teammates":[{"name":"Tangela","usage":48.94},{"name":"Porygon","usage":48.94},{"name":"Hattrem","usage":48.94},{"name":"Raboot","usage":48.94},{"name":"Marshtomp","usage":48.94}],"counters":[],"lead":{"usage":0.09998,"raw":16,"rawp":1.493}},"combusken":{"usage":0.08578,"raw":185,"avg":0.00186528036228,"vc":67,"abilities":[{"name":"Speed Boost","usage":100},{"name":"Blaze","usage":0}],"moves":[{"name":"Brick Break","usage":100},{"name":"Thunder Punch","usage":69.497},{"name":"Flare Blitz","usage":68.132},{"name":"Bulk Up","usage":67.873},{"name":"Swords Dance","usage":32.127},{"name":"Blaze Kick","usage":31.868},{"name":"Protect","usage":30.503},{"name":"Other","usage":0}],"items":[{"name":"Sitrus Berry","usage":67.873},{"name":"Leftovers","usage":31.868},{"name":"Other","usage":0.259}],"spreads":[{"nature":"Adamant","evs":{"hp":0,"atk":252,"def":4,"spa":0,"spd":0,"spe":252},"usage":67.873},{"nature":"Adamant","evs":{"hp":0,"atk":252,"def":0,"spa":0,"spd":4,"spe":252},"usage":30.326},{"nature":"Other","evs":{"hp":null,"atk":null,"def":null,"spa":null,"spd":null,"spe":null},"usage":1.8}],"teammates":[{"name":"Raboot","usage":36.559},{"name":"Growlithe","usage":35.018},{"name":"Torracat","usage":35.018},{"name":"Lampent","usage":35.018},{"name":"Magmar","usage":35.018},{"name":"Thwackey","usage":1.624},{"name":"Zweilous","usage":1.542},{"name":"Ivysaur","usage":1.542},{"name":"Dusclops","usage":1.542}],"counters":[],"lead":{"usage":0,"raw":25,"rawp":2.332}},"lampent":{"usage":0.08204,"raw":47,"avg":0.0115853605453,"vc":62,"abilities":[{"name":"Infiltrator","usage":99.716},{"name":"Flash Fire","usage":0.284},{"name":"Flame Body","usage":0}],"moves":[{"name":"Shadow Ball","usage":100},{"name":"Energy Ball","usage":100},{"name":"Calm Mind","usage":99.716},{"name":"Flamethrower","usage":99.716},{"name":"Other","usage":0.567}],"items":[{"name":"Eviolite","usage":99.716},{"name":"Other","usage":0.284}],"spreads":[{"nature":"Modest","evs":{"hp":248,"atk":0,"def":0,"spa":252,"spd":8,"spe":0},"usage":99.716},{"nature":"Other","evs":{"hp":null,"atk":null,"def":null,"spa":null,"spd":null,"spe":null},"usage":0.284}],"teammates":[{"name":"Growlithe","usage":51.446},{"name":"Torracat","usage":51.446},{"name":"Combusken","usage":51.446},{"name":"Raboot","usage":51.446},{"name":"Magmar","usage":51.446}],"counters":[],"lead":{"usage":0.04878,"raw":4,"rawp":0.373}},"growlithe":{"usage":0.08159,"raw":4,"avg":0.0308066353339,"vc":62,"abilities":[{"name":"Intimidate","usage":100},{"name":"Flash Fire","usage":0}],"moves":[{"name":"Close Combat","usage":100},{"name":"Morning Sun","usage":100},{"name":"Flare Blitz","usage":100},{"name":"Toxic","usage":100},{"name":"Other","usage":0}],"items":[{"name":"Heavy-Duty Boots","usage":100},{"name":"Other","usage":0}],"spreads":[{"nature":"Careful","evs":{"hp":252,"atk":4,"def":0,"spa":0,"spd":252,"spe":0},"usage":100},{"nature":"Other","evs":{"hp":null,"atk":null,"def":null,"spa":null,"spd":null,"spe":null},"usage":0}],"teammates":[{"name":"Lampent","usage":51.593},{"name":"Raboot","usage":51.593},{"name":"Magmar","usage":51.593},{"name":"Combusken","usage":51.593},{"name":"Torracat","usage":51.593}],"counters":[],"lead":{"usage":0,"raw":0,"rawp":0}},"shelgon":{"usage":0.06599,"raw":40,"avg":0.0101086012198,"vc":66,"abilities":[{"name":"Overcoat","usage":100},{"name":"Rock Head","usage":0}],"moves":[{"name":"Crunch","usage":100},{"name":"Rock Slide","usage":100},{"name":"Outrage","usage":100},{"name":"Dragon Dance","usage":93.808},{"name":"Other","usage":6.192}],"items":[{"name":"Eviolite","usage":100},{"name":"Other","usage":0}],"spreads":[{"nature":"Jolly","evs":{"hp":0,"atk":252,"def":0,"spa":0,"spd":4,"spe":252},"usage":93.808},{"nature":"Adamant","evs":{"hp":252,"atk":252,"def":0,"spa":0,"spd":4,"spe":0},"usage":6.192},{"nature":"Other","evs":{"hp":null,"atk":null,"def":null,"spa":null,"spd":null,"spe":null},"usage":0}],"teammates":[{"name":"Piloswine","usage":93.808},{"name":"Electabuzz","usage":93.808},{"name":"Omanyte","usage":93.808},{"name":"Hattrem","usage":93.808},{"name":"Thwackey","usage":93.808},{"name":"Linoone-Galar","usage":1.581},{"name":"Brionne","usage":1.581},{"name":"Tangela","usage":1.581},{"name":"Dusclops","usage":1.581},{"name":"Dusclops","usage":1.581}],"counters":[],"lead":{"usage":0,"raw":3,"rawp":0.28}},"omanyte":{"usage":0.0649,"raw":27,"avg":0.00474134528963,"vc":66,"abilities":[{"name":"Shell Armor","usage":100},{"name":"Swift Swim","usage":0},{"name":"Weak Armor","usage":0}],"moves":[{"name":"Surf","usage":100},{"name":"Earth Power","usage":100},{"name":"Shell Smash","usage":100},{"name":"Ice Beam","usage":100},{"name":"Other","usage":0}],"items":[{"name":"Focus Sash","usage":100},{"name":"Other","usage":0}],"spreads":[{"nature":"Timid","evs":{"hp":0,"atk":0,"def":0,"spa":252,"spd":4,"spe":252},"usage":100},{"nature":"Other","evs":{"hp":null,"atk":null,"def":null,"spa":null,"spd":null,"spe":null},"usage":0}],"teammates":[{"name":"Shelgon","usage":100},{"name":"Piloswine","usage":100},{"name":"Electabuzz","usage":100},{"name":"Hattrem","usage":100},{"name":"Thwackey","usage":100},{"name":"Thwackey","usage":100}],"counters":[],"lead":{"usage":0.03657,"raw":3,"rawp":0.28}},"palpitoad":{"usage":0.05559,"raw":20,"avg":0.00766075525994,"vc":63,"abilities":[{"name":"Water Absorb","usage":100},{"name":"Swift Swim","usage":0}],"moves":[{"name":"Sludge Bomb","usage":100},{"name":"Earth Power","usage":100},{"name":"Hyper Voice","usage":100},{"name":"Icy Wind","usage":100},{"name":"Other","usage":0}],"items":[{"name":"Choice Scarf","usage":100},{"name":"Other","usage":0}],"spreads":[{"nature":"Timid","evs":{"hp":0,"atk":0,"def":0,"spa":252,"spd":4,"spe":252},"usage":100},{"nature":"Other","evs":{"hp":null,"atk":null,"def":null,"spa":null,"spd":null,"spe":null},"usage":0}],"teammates":[{"name":"Linoone-Galar","usage":70.678},{"name":"Tangela","usage":70.678},{"name":"Porygon","usage":70.678},{"name":"Golbat","usage":70.678},{"name":"Dusclops","usage":70.678}],"counters":[],"lead":{"usage":0,"raw":2,"rawp":0.187}},"sliggoo":{"usage":0.05204,"raw":73,"avg":0.00356740061766,"vc":60,"abilities":[{"name":"Gooey","usage":97.795},{"name":"Hydration","usage":2.205},{"name":"Sap Sipper","usage":0}],"moves":[{"name":"Dragon Pulse","usage":99.962},{"name":"Thunderbolt","usage":97.795},{"name":"Ice Beam","usage":97.795},{"name":"Toxic","usage":97.757},{"name":"Other","usage":6.692}],"items":[{"name":"Eviolite","usage":100},{"name":"Other","usage":0}],"spreads":[{"nature":"Modest","evs":{"hp":0,"atk":0,"def":252,"spa":252,"spd":4,"spe":0},"usage":97.757},{"nature":"Other","evs":{"hp":null,"atk":null,"def":null,"spa":null,"spd":null,"spe":null},"usage":2.243}],"teammates":[{"name":"Thwackey","usage":44.874},{"name":"Dusclops","usage":44.874},{"name":"Abra","usage":42.668},{"name":"Golbat","usage":42.668},{"name":"Magmar","usage":42.668},{"name":"Morgrem","usage":2.205},{"name":"Poliwhirl","usage":2.205},{"name":"Electabuzz","usage":2.205}],"counters":[],"lead":{"usage":0,"raw":14,"rawp":1.306}},"dottler":{"usage":0.0143,"raw":21,"avg":0.0016714191719,"vc":60,"abilities":[{"name":"Compound Eyes","usage":100},{"name":"Swarm","usage":0}],"moves":[{"name":"Sticky Web","usage":100},{"name":"Psychic","usage":100},{"name":"Bug Buzz","usage":100},{"name":"Recover","usage":100},{"name":"Other","usage":0}],"items":[{"name":"Leftovers","usage":100},{"name":"Other","usage":0}],"spreads":[{"nature":"Calm","evs":{"hp":248,"atk":0,"def":0,"spa":8,"spd":252,"spe":0},"usage":100},{"nature":"Other","evs":{"hp":null,"atk":null,"def":null,"spa":null,"spd":null,"spe":null},"usage":0}],"teammates":[{"name":"Gurdurr","usage":100},{"name":"Corsola-Galar","usage":100},{"name":"Hattrem","usage":100},{"name":"Clefairy","usage":100},{"name":"Herdier","usage":100},{"name":"Herdier","usage":100}],"counters":[],"lead":{"usage":0,"raw":6,"rawp":0.56}},"carkol":{"usage":0.01084,"raw":52,"avg":0.000351889489434,"vc":56,"abilities":[{"name":"Flame Body","usage":100},{"name":"Flash Fire","usage":0},{"name":"Steam Engine","usage":0}],"moves":[{"name":"Body Press","usage":100},{"name":"Iron Defense","usage":84.074},{"name":"Rest","usage":69.182},{"name":"Sleep Talk","usage":69.182},{"name":"Stealth Rock","usage":30.818},{"name":"Gyro Ball","usage":15.926},{"name":"Flare Blitz","usage":15.926},{"name":"Other","usage":14.892}],"items":[{"name":"Eviolite","usage":100},{"name":"Other","usage":0}],"spreads":[{"nature":"Calm","evs":{"hp":248,"atk":0,"def":8,"spa":0,"spd":252,"spe":0},"usage":69.182},{"nature":"Brave","evs":{"hp":248,"atk":252,"def":0,"spa":0,"spd":8,"spe":0},"usage":15.926},{"nature":"Calm","evs":{"hp":248,"atk":0,"def":8,"spa":0,"spd":116,"spe":136},"usage":14.892},{"nature":"Other","evs":{"hp":null,"atk":null,"def":null,"spa":null,"spd":null,"spe":null},"usage":0}],"teammates":[{"name":"Gurdurr","usage":81.114},{"name":"Slowpoke-Galar","usage":69.182},{"name":"Ferroseed","usage":69.182},{"name":"Meowth-Alola","usage":69.182},{"name":"Mareanie","usage":69.182},{"name":"Duosion","usage":11.932},{"name":"Electabuzz","usage":11.932},{"name":"Thwackey","usage":11.932},{"name":"Clefairy","usage":11.932},{"name":"Linoone-Galar","usage":4.632},{"name":"Tangela","usage":4.632}],"counters":[],"lead":{"usage":0.0015,"raw":22,"rawp":2.052}}}